{"ID":119,"Title":"My Name Is Earl","Released":"2005-09-20T00:00:00Z","Runtime":30,"Writer":"Gregory Thomas Garcia","Actors":"Jason Lee, Ethan Suplee, Jaime Pressly, Eddie Steeples, Nadine Velazquez","Plot":"Earl is a low-life who buys a winning lottery ticket, only to get hit by a car, losing the ticket in the process. He then realizes in the hospital that his bad luck is the result of karma in which fate punishes him for all the rotten things he's ever done in his life; therefore, he then decides to dedicate his life to making amends to all the people he has hurt in his life.","Poster":"http://thetvdb.com/banners/posters/75397-2.jpg","Fanart":"http://thetvdb.com/banners/fanart/original/75397-17.jpg","Rating":7.800000190734863,"RatingCount":76833,"Categories":[0,20,37],"DateCreated":"2014-06-29T00:18:11Z","ParentalRating":"M","IMDB":"tt0460091","TVDB":75397,"Seasons":[{"ID":351,"ShowID":119,"DateCreated":"2014-06-30T05:37:05Z","Number":1,"ParentalRating":"M","Image":"http://thetvdb.com/banners/seasons/31988-1.jpg","TVDB":8835,"EpisodeCount":24},{"ID":352,"ShowID":119,"DateCreated":"2014-06-30T05:38:35Z","Number":2,"ParentalRating":"M","Image":"http://thetvdb.com/banners/seasons/31988-2.jpg","TVDB":16331,"EpisodeCount":23},{"ID":359,"ShowID":119,"DateCreated":"2014-07-01T07:42:31Z","Number":3,"ParentalRating":"M","Image":"http://thetvdb.com/banners/seasons/75397-3.jpg","TVDB":16712,"EpisodeCount":22},{"ID":338,"ShowID":119,"DateCreated":"2014-06-29T00:18:11Z","Number":4,"ParentalRating":"M","Image":"http://thetvdb.com/banners/seasons/75397-4.jpg","TVDB":35408,"EpisodeCount":27}]}
