<?xml version="1.0" encoding="UTF-8" ?>
<Actors>
<Actor>
  <id>317440</id>
  <Image>actors/317440.jpg</Image>
  <Name>Ashley Walters</Name>
  <Role>Dushane</Role>
  <SortOrder>0</SortOrder>
</Actor>
<Actor>
  <id>291409</id>
  <Image>actors/291409.jpg</Image>
  <Name>Kane Robinson</Name>
  <Role>Sully</Role>
  <SortOrder>1</SortOrder>
</Actor>
<Actor>
  <id>317439</id>
  <Image>actors/317439.jpg</Image>
  <Name>Ra'Nell</Name>
  <Role>Malcolm Kamulete</Role>
  <SortOrder>2</SortOrder>
</Actor>
<Actor>
  <id>317445</id>
  <Image>actors/317445.jpg</Image>
  <Name>Sean Sagar</Name>
  <Role>Tareek</Role>
  <SortOrder>3</SortOrder>
</Actor>
<Actor>
  <id>317444</id>
  <Image>actors/317444.jpg</Image>
  <Name>Geoff Bell</Name>
  <Role>Bobby Raikes</Role>
  <SortOrder>3</SortOrder>
</Actor>
<Actor>
  <id>317443</id>
  <Image>actors/317443.jpg</Image>
  <Name>Benedict Wong</Name>
  <Role>Vincent </Role>
  <SortOrder>3</SortOrder>
</Actor>
<Actor>
  <id>317442</id>
  <Image>actors/317442.jpg</Image>
  <Name>Kierston Wareing</Name>
  <Role>Heather</Role>
  <SortOrder>3</SortOrder>
</Actor>
<Actor>
  <id>317441</id>
  <Image>actors/317441.jpg</Image>
  <Name>Sharon Duncan-Brewster</Name>
  <Role>Lisa</Role>
  <SortOrder>3</SortOrder>
</Actor>
<Actor>
  <id>291413</id>
  <Image>actors/291413.jpg</Image>
  <Name>Tayo 'Scorcher' Jarrett</Name>
  <Role>Kamale</Role>
  <SortOrder>3</SortOrder>
</Actor>
<Actor>
  <id>291412</id>
  <Image>actors/291412.jpg</Image>
  <Name>Shone Romulus</Name>
  <Role>Dris</Role>
  <SortOrder>3</SortOrder>
</Actor>
<Actor>
  <id>291411</id>
  <Image>actors/291411.jpg</Image>
  <Name>Nicholas Pinnock</Name>
  <Role>Leon</Role>
  <SortOrder>3</SortOrder>
</Actor>
<Actor>
  <id>291410</id>
  <Image>actors/291410.jpg</Image>
  <Name>Letitia Wright</Name>
  <Role>Chantelle</Role>
  <SortOrder>3</SortOrder>
</Actor>
<Actor>
  <id>291408</id>
  <Image>actors/291408.jpg</Image>
  <Name>Giacomo Mancini</Name>
  <Role>Gem</Role>
  <SortOrder>3</SortOrder>
</Actor>
</Actors>