<?xml version="1.0" encoding="UTF-8" ?>
<Banners>
<Banner>
  <id>235521</id>
  <BannerPath>fanart/original/78685-2.jpg</BannerPath>
  <BannerType>fanart</BannerType>
  <BannerType2>1920x1080</BannerType2>
  <Colors></Colors>
  <Language>en</Language>
  <Rating>10.0000</Rating>
  <RatingCount>1</RatingCount>
  <SeriesName>false</SeriesName>
  <ThumbnailPath>_cache/fanart/original/78685-2.jpg</ThumbnailPath>
  <VignettePath>fanart/vignette/78685-2.jpg</VignettePath>
</Banner>
<Banner>
  <id>120561</id>
  <BannerPath>fanart/original/78685-1.jpg</BannerPath>
  <BannerType>fanart</BannerType>
  <BannerType2>1920x1080</BannerType2>
  <Colors>|193,211,235|182,7,14|248,213,193|</Colors>
  <Language>en</Language>
  <Rating>7.0000</Rating>
  <RatingCount>1</RatingCount>
  <SeriesName>true</SeriesName>
  <ThumbnailPath>_cache/fanart/original/78685-1.jpg</ThumbnailPath>
  <VignettePath>fanart/vignette/78685-1.jpg</VignettePath>
</Banner>
<Banner>
  <id>355471</id>
  <BannerPath>posters/78685-2.jpg</BannerPath>
  <BannerType>poster</BannerType>
  <BannerType2>680x1000</BannerType2>
  <Language>en</Language>
  <Rating>9.6667</Rating>
  <RatingCount>3</RatingCount>
</Banner>
<Banner>
  <id>940309</id>
  <BannerPath>posters/78685-4.jpg</BannerPath>
  <BannerType>poster</BannerType>
  <BannerType2>680x1000</BannerType2>
  <Language>en</Language>
  <Rating>8.5000</Rating>
  <RatingCount>2</RatingCount>
</Banner>
<Banner>
  <id>42672</id>
  <BannerPath>posters/78685-1.jpg</BannerPath>
  <BannerType>poster</BannerType>
  <BannerType2>680x1000</BannerType2>
  <Language>en</Language>
  <Rating>7.0000</Rating>
  <RatingCount>1</RatingCount>
</Banner>
<Banner>
  <id>526631</id>
  <BannerPath>posters/78685-3.jpg</BannerPath>
  <BannerType>poster</BannerType>
  <BannerType2>680x1000</BannerType2>
  <Language>en</Language>
  <Rating>6.0000</Rating>
  <RatingCount>1</RatingCount>
</Banner>
<Banner>
  <id>367771</id>
  <BannerPath>seasons/78685-0.jpg</BannerPath>
  <BannerType>season</BannerType>
  <BannerType2>season</BannerType2>
  <Language>en</Language>
  <Rating>10.0000</Rating>
  <RatingCount>1</RatingCount>
  <Season>0</Season>
</Banner>
<Banner>
  <id>17610</id>
  <BannerPath>seasons/78685-1.jpg</BannerPath>
  <BannerType>season</BannerType>
  <BannerType2>season</BannerType2>
  <Language>en</Language>
  <Rating>10.0000</Rating>
  <RatingCount>1</RatingCount>
  <Season>1</Season>
</Banner>
<Banner>
  <id>526601</id>
  <BannerPath>seasons/78685-1-2.jpg</BannerPath>
  <BannerType>season</BannerType>
  <BannerType2>season</BannerType2>
  <Language>cs</Language>
  <Rating>7.0000</Rating>
  <RatingCount>1</RatingCount>
  <Season>1</Season>
</Banner>
<Banner>
  <id>17630</id>
  <BannerPath>seasons/78685-9.jpg</BannerPath>
  <BannerType>season</BannerType>
  <BannerType2>season</BannerType2>
  <Language>en</Language>
  <Rating></Rating>
  <RatingCount>0</RatingCount>
  <Season>9</Season>
</Banner>
<Banner>
  <id>17627</id>
  <BannerPath>seasons/78685-6.jpg</BannerPath>
  <BannerType>season</BannerType>
  <BannerType2>season</BannerType2>
  <Language>en</Language>
  <Rating></Rating>
  <RatingCount>0</RatingCount>
  <Season>6</Season>
</Banner>
<Banner>
  <id>17613</id>
  <BannerPath>seasons/78685-5.jpg</BannerPath>
  <BannerType>season</BannerType>
  <BannerType2>season</BannerType2>
  <Language>en</Language>
  <Rating></Rating>
  <RatingCount>0</RatingCount>
  <Season>5</Season>
</Banner>
<Banner>
  <id>17612</id>
  <BannerPath>seasons/78685-4.jpg</BannerPath>
  <BannerType>season</BannerType>
  <BannerType2>season</BannerType2>
  <Language>en</Language>
  <Rating></Rating>
  <RatingCount>0</RatingCount>
  <Season>4</Season>
</Banner>
<Banner>
  <id>17629</id>
  <BannerPath>seasons/78685-8.jpg</BannerPath>
  <BannerType>season</BannerType>
  <BannerType2>season</BannerType2>
  <Language>en</Language>
  <Rating></Rating>
  <RatingCount>0</RatingCount>
  <Season>8</Season>
</Banner>
<Banner>
  <id>17628</id>
  <BannerPath>seasons/78685-7.jpg</BannerPath>
  <BannerType>season</BannerType>
  <BannerType2>season</BannerType2>
  <Language>en</Language>
  <Rating></Rating>
  <RatingCount>0</RatingCount>
  <Season>7</Season>
</Banner>
<Banner>
  <id>17609</id>
  <BannerPath>seasons/78685-2.jpg</BannerPath>
  <BannerType>season</BannerType>
  <BannerType2>season</BannerType2>
  <Language>en</Language>
  <Rating></Rating>
  <RatingCount>0</RatingCount>
  <Season>2</Season>
</Banner>
<Banner>
  <id>17611</id>
  <BannerPath>seasons/78685-3.jpg</BannerPath>
  <BannerType>season</BannerType>
  <BannerType2>season</BannerType2>
  <Language>en</Language>
  <Rating></Rating>
  <RatingCount>0</RatingCount>
  <Season>3</Season>
</Banner>
<Banner>
  <id>949954</id>
  <BannerPath>seasons/78685-10.jpg</BannerPath>
  <BannerType>season</BannerType>
  <BannerType2>season</BannerType2>
  <Language>en</Language>
  <Rating></Rating>
  <RatingCount>0</RatingCount>
  <Season>10</Season>
</Banner>
<Banner>
  <id>355481</id>
  <BannerPath>graphical/78685-g2.jpg</BannerPath>
  <BannerType>series</BannerType>
  <BannerType2>graphical</BannerType2>
  <Language>en</Language>
  <Rating>10.0000</Rating>
  <RatingCount>1</RatingCount>
</Banner>
<Banner>
  <id>17608</id>
  <BannerPath>graphical/78685-g.jpg</BannerPath>
  <BannerType>series</BannerType>
  <BannerType2>graphical</BannerType2>
  <Language>en</Language>
  <Rating>8.0000</Rating>
  <RatingCount>1</RatingCount>
</Banner>
</Banners>