<?xml version="1.0" encoding="UTF-8" ?>
<Data><Series>
  <id>264888</id>
  <Actors>||</Actors>
  <Airs_DayOfWeek>Friday</Airs_DayOfWeek>
  <Airs_Time></Airs_Time>
  <ContentRating>TV-G</ContentRating>
  <FirstAired>2011-01-14</FirstAired>
  <Genre>|Children|</Genre>
  <IMDB_ID>tt1824698</IMDB_ID>
  <Language>en</Language>
  <Network>CBBC</Network>
  <NetworkID></NetworkID>
  <Overview>Sadie Jenkins is the only girl in an all-boy household. Even the dog is male! Sadie is growing up. She's a young lady and she wants to be treated like one! However, Sadie's journey from tomboy to girly girl isn't going to be an easy one. From fashion faux pas to disastrous dates and makeup meltdowns, who knew growing up could be this tough?
</Overview>
  <Rating></Rating>
  <RatingCount>0</RatingCount>
  <Runtime>30</Runtime>
  <SeriesID></SeriesID>
  <SeriesName>Sadie J</SeriesName>
  <Status>Continuing</Status>
  <added>2012-12-14 18:06:02</added>
  <addedBy>83</addedBy>
  <banner></banner>
  <fanart></fanart>
  <lastupdated>1423170767</lastupdated>
  <poster>posters/264888-1.jpg</poster>
  <tms_wanted_old>0</tms_wanted_old>
  <zap2it_id></zap2it_id>
</Series>
<Episode>
  <id>4454994</id>
  <Combined_episodenumber>1</Combined_episodenumber>
  <Combined_season>1</Combined_season>
  <DVD_chapter></DVD_chapter>
  <DVD_discid></DVD_discid>
  <DVD_episodenumber></DVD_episodenumber>
  <DVD_season></DVD_season>
  <Director></Director>
  <EpImgFlag></EpImgFlag>
  <EpisodeName>Crushamondo </EpisodeName>
  <EpisodeNumber>1</EpisodeNumber>
  <FirstAired>2011-01-14</FirstAired>
  <GuestStars></GuestStars>
  <IMDB_ID></IMDB_ID>
  <Language>en</Language>
  <Overview>Sadie falls for geek-turned-hottie Joe, but how can she compete with trog-face Chloe? 

By proving to him that she's not a grease monkey in overalls. Cue one of Kit's makeovers. 

</Overview>
  <ProductionCode></ProductionCode>
  <Rating></Rating>
  <RatingCount>0</RatingCount>
  <SeasonNumber>1</SeasonNumber>
  <Writer></Writer>
  <absolute_number></absolute_number>
  <filename></filename>
  <lastupdated>1418244099</lastupdated>
  <seasonid>507322</seasonid>
  <seriesid>264888</seriesid>
  <thumb_added></thumb_added>
  <thumb_height></thumb_height>
  <thumb_width></thumb_width>
</Episode>
<Episode>
  <id>4454995</id>
  <Combined_episodenumber>2</Combined_episodenumber>
  <Combined_season>1</Combined_season>
  <DVD_chapter></DVD_chapter>
  <DVD_discid></DVD_discid>
  <DVD_episodenumber></DVD_episodenumber>
  <DVD_season></DVD_season>
  <Director></Director>
  <EpImgFlag></EpImgFlag>
  <EpisodeName>Robobootylicious </EpisodeName>
  <EpisodeNumber>2</EpisodeNumber>
  <FirstAired>2011-01-21</FirstAired>
  <GuestStars></GuestStars>
  <IMDB_ID></IMDB_ID>
  <Language>en</Language>
  <Overview>Sadie fixes it for Dede's mum to come to the JLS concert with her, and gets Steve to help Dede with her robot wars fight night on the same night. 

Then Dede's mum turns out to be even less cool than Steve, so she tries to get her dad back, by sabotaging Dede's robot so he won't have to help her any more. 

</Overview>
  <ProductionCode></ProductionCode>
  <Rating></Rating>
  <RatingCount>0</RatingCount>
  <SeasonNumber>1</SeasonNumber>
  <Writer></Writer>
  <absolute_number></absolute_number>
  <filename></filename>
  <lastupdated>1418244116</lastupdated>
  <seasonid>507322</seasonid>
  <seriesid>264888</seriesid>
  <thumb_added></thumb_added>
  <thumb_height></thumb_height>
  <thumb_width></thumb_width>
</Episode>
<Episode>
  <id>4454996</id>
  <Combined_episodenumber>3</Combined_episodenumber>
  <Combined_season>1</Combined_season>
  <DVD_chapter></DVD_chapter>
  <DVD_discid></DVD_discid>
  <DVD_episodenumber></DVD_episodenumber>
  <DVD_season></DVD_season>
  <Director></Director>
  <EpImgFlag></EpImgFlag>
  <EpisodeName>Friendalicious </EpisodeName>
  <EpisodeNumber>3</EpisodeNumber>
  <FirstAired>2011-01-28</FirstAired>
  <GuestStars></GuestStars>
  <IMDB_ID></IMDB_ID>
  <Language>en</Language>
  <Overview>Sadie thinks that Kit has traded her in as his BFF for Chloe. So, she invents a cooler, richer, better best friend - and then has to have him meet Kit! 

</Overview>
  <ProductionCode></ProductionCode>
  <Rating></Rating>
  <RatingCount>0</RatingCount>
  <SeasonNumber>1</SeasonNumber>
  <Writer></Writer>
  <absolute_number></absolute_number>
  <filename></filename>
  <lastupdated>1418244133</lastupdated>
  <seasonid>507322</seasonid>
  <seriesid>264888</seriesid>
  <thumb_added></thumb_added>
  <thumb_height></thumb_height>
  <thumb_width></thumb_width>
</Episode>
<Episode>
  <id>4454997</id>
  <Combined_episodenumber>4</Combined_episodenumber>
  <Combined_season>1</Combined_season>
  <DVD_chapter></DVD_chapter>
  <DVD_discid></DVD_discid>
  <DVD_episodenumber></DVD_episodenumber>
  <DVD_season></DVD_season>
  <Director></Director>
  <EpImgFlag></EpImgFlag>
  <EpisodeName>Slumberlicious </EpisodeName>
  <EpisodeNumber>4</EpisodeNumber>
  <FirstAired>2011-02-04</FirstAired>
  <GuestStars></GuestStars>
  <IMDB_ID></IMDB_ID>
  <Language>en</Language>
  <Overview>Sadie is hosting a slumber party and wants all the sassy, A-list members of her school to be invited. (despite many being anything but her friends). 

But a typically clumsy Sadie then breaks a hi-tech teapot that Dede had slaved over 
Slumberlicious - Episode 4
Added by Mi28Havocmaking. Fearing Dede will force her to spend the night rebuilding the teapot - sabotaging her slumber party, Sadie first tries a cheap trick to frame Kit for the misdemeanor. It's a fail, so she hatches an elaborate plot about a &quot;lean-mean burgluring machine&quot; having broke into her room, and stolen the teapot! Just the teapot alone! As if! Dede isn't fooled for a single second - anyway, Roger later exposes Sadie's subterfuge to Dede! 
Sadie gets her party in the end - and they all even repair Dede's teapot whilst there - only for Kit to come barging in dressed as a bandit scaring them all half to death! Chaos ensues and Sadie has to choose between saving Dedes teapot or her own cherised choclate fountain. She makes the right choice in the end! 

</Overview>
  <ProductionCode></ProductionCode>
  <Rating></Rating>
  <RatingCount>0</RatingCount>
  <SeasonNumber>1</SeasonNumber>
  <Writer></Writer>
  <absolute_number></absolute_number>
  <filename></filename>
  <lastupdated>1418244155</lastupdated>
  <seasonid>507322</seasonid>
  <seriesid>264888</seriesid>
  <thumb_added></thumb_added>
  <thumb_height></thumb_height>
  <thumb_width></thumb_width>
</Episode>
<Episode>
  <id>4454998</id>
  <Combined_episodenumber>5</Combined_episodenumber>
  <Combined_season>1</Combined_season>
  <DVD_chapter></DVD_chapter>
  <DVD_discid></DVD_discid>
  <DVD_episodenumber></DVD_episodenumber>
  <DVD_season></DVD_season>
  <Director></Director>
  <EpImgFlag></EpImgFlag>
  <EpisodeName>Tidylicious </EpisodeName>
  <EpisodeNumber>5</EpisodeNumber>
  <FirstAired>2011-02-11</FirstAired>
  <GuestStars></GuestStars>
  <IMDB_ID></IMDB_ID>
  <Language>en</Language>
  <Overview>Sadie becomes sick of all the mess the boys leave behind - not even giving a thought to the fact she's caused half of it. Sadie rallies them all to assault the mess - but with rather poor results. So she decides it's time for a housekeeper - against her dad's wishes. 

Meanwhile Dede manages to construct a rather lethal looking M261 70mm Hydra rocket - but Jake and Danny nick it and replace the HEDP submunition filled warhead with custard..... shame, the original would have definately cleared the room out for Sadie! 

Sadie, Kit and Dede interview a load of looney housekeepers, none of them seem any use - Sadie gives up on the idea - just as the perfect housekeeper turns up out of nowhere. 

At first she's amazing! The Jenkins are all astounded with her performance, and Sadie especially, as she gets treated like &quot;a young lady&quot;. But they don't stop to ask &quot;is this too perfect?&quot;. Not till she starts to turn out to be a Glenn Close type bunny boiler! 

Finally Jake and Danny use the Hydra rocket against the housekeeper (should've left the HEDP bomblets in it guys!) giving her a good showering of custard - at which point she goes pyschonaut lashing out at Jake, Danny and Sadie. Bad move! She didn't realise Steve was also witnessing it all. One fired housekeep! 

</Overview>
  <ProductionCode></ProductionCode>
  <Rating></Rating>
  <RatingCount>0</RatingCount>
  <SeasonNumber>1</SeasonNumber>
  <Writer></Writer>
  <absolute_number></absolute_number>
  <filename></filename>
  <lastupdated>1418244173</lastupdated>
  <seasonid>507322</seasonid>
  <seriesid>264888</seriesid>
  <thumb_added></thumb_added>
  <thumb_height></thumb_height>
  <thumb_width></thumb_width>
</Episode>
<Episode>
  <id>4454999</id>
  <Combined_episodenumber>6</Combined_episodenumber>
  <Combined_season>1</Combined_season>
  <DVD_chapter></DVD_chapter>
  <DVD_discid></DVD_discid>
  <DVD_episodenumber></DVD_episodenumber>
  <DVD_season></DVD_season>
  <Director></Director>
  <EpImgFlag></EpImgFlag>
  <EpisodeName>Fashiontastic </EpisodeName>
  <EpisodeNumber>6</EpisodeNumber>
  <FirstAired>2011-02-18</FirstAired>
  <GuestStars></GuestStars>
  <IMDB_ID></IMDB_ID>
  <Language>en</Language>
  <Overview>Sadie discovers she has no fashion sense when Kit lets her design a costume. 

</Overview>
  <ProductionCode></ProductionCode>
  <Rating></Rating>
  <RatingCount>0</RatingCount>
  <SeasonNumber>1</SeasonNumber>
  <Writer></Writer>
  <absolute_number></absolute_number>
  <filename></filename>
  <lastupdated>1418244240</lastupdated>
  <seasonid>507322</seasonid>
  <seriesid>264888</seriesid>
  <thumb_added></thumb_added>
  <thumb_height></thumb_height>
  <thumb_width></thumb_width>
</Episode>
<Episode>
  <id>4455000</id>
  <Combined_episodenumber>7</Combined_episodenumber>
  <Combined_season>1</Combined_season>
  <DVD_chapter></DVD_chapter>
  <DVD_discid></DVD_discid>
  <DVD_episodenumber></DVD_episodenumber>
  <DVD_season></DVD_season>
  <Director></Director>
  <EpImgFlag></EpImgFlag>
  <EpisodeName>Partylicious </EpisodeName>
  <EpisodeNumber>7</EpisodeNumber>
  <FirstAired>2011-02-25</FirstAired>
  <GuestStars></GuestStars>
  <IMDB_ID></IMDB_ID>
  <Language>en</Language>
  <Overview>Sadie's thinks she is too old to have a birthday organised by her dad, so she tries to help Kit and Dede organise her own surprise party. 

</Overview>
  <ProductionCode></ProductionCode>
  <Rating></Rating>
  <RatingCount>0</RatingCount>
  <SeasonNumber>1</SeasonNumber>
  <Writer></Writer>
  <absolute_number></absolute_number>
  <filename></filename>
  <lastupdated>1418244261</lastupdated>
  <seasonid>507322</seasonid>
  <seriesid>264888</seriesid>
  <thumb_added></thumb_added>
  <thumb_height></thumb_height>
  <thumb_width></thumb_width>
</Episode>
<Episode>
  <id>4455001</id>
  <Combined_episodenumber>8</Combined_episodenumber>
  <Combined_season>1</Combined_season>
  <DVD_chapter></DVD_chapter>
  <DVD_discid></DVD_discid>
  <DVD_episodenumber></DVD_episodenumber>
  <DVD_season></DVD_season>
  <Director></Director>
  <EpImgFlag></EpImgFlag>
  <EpisodeName>Pompomtastic </EpisodeName>
  <EpisodeNumber>8</EpisodeNumber>
  <FirstAired>2011-03-04</FirstAired>
  <GuestStars></GuestStars>
  <IMDB_ID></IMDB_ID>
  <Language>en</Language>
  <Overview>Sadie's thinks she is too old to have a birthday organised by her dad, so she tries to help Kit and Dede organise her own surprise party. 

</Overview>
  <ProductionCode></ProductionCode>
  <Rating></Rating>
  <RatingCount>0</RatingCount>
  <SeasonNumber>1</SeasonNumber>
  <Writer></Writer>
  <absolute_number></absolute_number>
  <filename></filename>
  <lastupdated>1418244282</lastupdated>
  <seasonid>507322</seasonid>
  <seriesid>264888</seriesid>
  <thumb_added></thumb_added>
  <thumb_height></thumb_height>
  <thumb_width></thumb_width>
</Episode>
<Episode>
  <id>4455002</id>
  <Combined_episodenumber>9</Combined_episodenumber>
  <Combined_season>1</Combined_season>
  <DVD_chapter></DVD_chapter>
  <DVD_discid></DVD_discid>
  <DVD_episodenumber></DVD_episodenumber>
  <DVD_season></DVD_season>
  <Director></Director>
  <EpImgFlag></EpImgFlag>
  <EpisodeName>Cherylistic </EpisodeName>
  <EpisodeNumber>9</EpisodeNumber>
  <FirstAired>2011-03-11</FirstAired>
  <GuestStars></GuestStars>
  <IMDB_ID></IMDB_ID>
  <Language>en</Language>
  <Overview>Sadie accidentally promises to get an A-list celeb for a Save-the-Y-Club concert - so she ends trying, then lying, then finally impersonating Cheryl Cole herself. 


</Overview>
  <ProductionCode></ProductionCode>
  <Rating></Rating>
  <RatingCount>0</RatingCount>
  <SeasonNumber>1</SeasonNumber>
  <Writer></Writer>
  <absolute_number></absolute_number>
  <filename></filename>
  <lastupdated>1418244298</lastupdated>
  <seasonid>507322</seasonid>
  <seriesid>264888</seriesid>
  <thumb_added></thumb_added>
  <thumb_height></thumb_height>
  <thumb_width></thumb_width>
</Episode>
<Episode>
  <id>4455003</id>
  <Combined_episodenumber>10</Combined_episodenumber>
  <Combined_season>1</Combined_season>
  <DVD_chapter></DVD_chapter>
  <DVD_discid></DVD_discid>
  <DVD_episodenumber></DVD_episodenumber>
  <DVD_season></DVD_season>
  <Director></Director>
  <EpImgFlag></EpImgFlag>
  <EpisodeName>Tiptastic </EpisodeName>
  <EpisodeNumber>10</EpisodeNumber>
  <FirstAired>2011-03-11</FirstAired>
  <GuestStars></GuestStars>
  <IMDB_ID></IMDB_ID>
  <Language>en</Language>
  <Overview>Sadie needs more money, so she becomes a roller-skating waitress in the Y - only to see Chloe walk off with her hard-earned cash. 


</Overview>
  <ProductionCode></ProductionCode>
  <Rating></Rating>
  <RatingCount>0</RatingCount>
  <SeasonNumber>1</SeasonNumber>
  <Writer></Writer>
  <absolute_number></absolute_number>
  <filename></filename>
  <lastupdated>1418244316</lastupdated>
  <seasonid>507322</seasonid>
  <seriesid>264888</seriesid>
  <thumb_added></thumb_added>
  <thumb_height></thumb_height>
  <thumb_width></thumb_width>
</Episode>
<Episode>
  <id>4455004</id>
  <Combined_episodenumber>11</Combined_episodenumber>
  <Combined_season>1</Combined_season>
  <DVD_chapter></DVD_chapter>
  <DVD_discid></DVD_discid>
  <DVD_episodenumber></DVD_episodenumber>
  <DVD_season></DVD_season>
  <Director></Director>
  <EpImgFlag></EpImgFlag>
  <EpisodeName>Promalicious</EpisodeName>
  <EpisodeNumber>11</EpisodeNumber>
  <FirstAired>2011-03-18</FirstAired>
  <GuestStars></GuestStars>
  <IMDB_ID></IMDB_ID>
  <Language>en</Language>
  <Overview>Desperate to shine at the Y prom, Sadie infiltrates Kit's Glee-style show-choir and steals the show
</Overview>
  <ProductionCode></ProductionCode>
  <Rating></Rating>
  <RatingCount>0</RatingCount>
  <SeasonNumber>1</SeasonNumber>
  <Writer></Writer>
  <absolute_number></absolute_number>
  <filename></filename>
  <lastupdated>1418244328</lastupdated>
  <seasonid>507322</seasonid>
  <seriesid>264888</seriesid>
  <thumb_added></thumb_added>
  <thumb_height></thumb_height>
  <thumb_width></thumb_width>
</Episode>
<Episode>
  <id>4455005</id>
  <Combined_episodenumber>12</Combined_episodenumber>
  <Combined_season>1</Combined_season>
  <DVD_chapter></DVD_chapter>
  <DVD_discid></DVD_discid>
  <DVD_episodenumber></DVD_episodenumber>
  <DVD_season></DVD_season>
  <Director></Director>
  <EpImgFlag></EpImgFlag>
  <EpisodeName>Girltastic, Part 1 </EpisodeName>
  <EpisodeNumber>12</EpisodeNumber>
  <FirstAired>2011-03-25</FirstAired>
  <GuestStars></GuestStars>
  <IMDB_ID></IMDB_ID>
  <Language>en</Language>
  <Overview>A journalist from a major teen magazine comes to visit to see if Sadie is good enough to be Tweenager of the Year. 

</Overview>
  <ProductionCode></ProductionCode>
  <Rating></Rating>
  <RatingCount>0</RatingCount>
  <SeasonNumber>1</SeasonNumber>
  <Writer></Writer>
  <absolute_number></absolute_number>
  <filename></filename>
  <lastupdated>1418244340</lastupdated>
  <seasonid>507322</seasonid>
  <seriesid>264888</seriesid>
  <thumb_added></thumb_added>
  <thumb_height></thumb_height>
  <thumb_width></thumb_width>
</Episode>
<Episode>
  <id>4455020</id>
  <Combined_episodenumber>13</Combined_episodenumber>
  <Combined_season>1</Combined_season>
  <DVD_chapter></DVD_chapter>
  <DVD_discid></DVD_discid>
  <DVD_episodenumber></DVD_episodenumber>
  <DVD_season></DVD_season>
  <Director></Director>
  <EpImgFlag></EpImgFlag>
  <EpisodeName>Girltastic, Part 2 </EpisodeName>
  <EpisodeNumber>13</EpisodeNumber>
  <FirstAired>2011-03-25</FirstAired>
  <GuestStars></GuestStars>
  <IMDB_ID></IMDB_ID>
  <Language>en</Language>
  <Overview>When Steve and Keith discover that Sadie's main competition for Girltastic Girl of the Year is Whitney, the captain of the Cheerups, they have their work cut out to convince the journo that Sadie is better - but things go wrong when Steve and Whitney have a fight in the Y. 

</Overview>
  <ProductionCode></ProductionCode>
  <Rating></Rating>
  <RatingCount>0</RatingCount>
  <SeasonNumber>1</SeasonNumber>
  <Writer></Writer>
  <absolute_number></absolute_number>
  <filename></filename>
  <lastupdated>1418244351</lastupdated>
  <seasonid>507322</seasonid>
  <seriesid>264888</seriesid>
  <thumb_added></thumb_added>
  <thumb_height></thumb_height>
  <thumb_width></thumb_width>
</Episode>
<Episode>
  <id>4455006</id>
  <Combined_episodenumber>1</Combined_episodenumber>
  <Combined_season>2</Combined_season>
  <DVD_chapter></DVD_chapter>
  <DVD_discid></DVD_discid>
  <DVD_episodenumber></DVD_episodenumber>
  <DVD_season></DVD_season>
  <Director></Director>
  <EpImgFlag></EpImgFlag>
  <EpisodeName>Kissalicious </EpisodeName>
  <EpisodeNumber>1</EpisodeNumber>
  <FirstAired>2012-01-25</FirstAired>
  <GuestStars></GuestStars>
  <IMDB_ID></IMDB_ID>
  <Language>en</Language>
  <Overview>Sadie has a crush on Taylor Bell, the new boy in town - but she quickly discovers that his girlfriend is the monstrous Ashlii.

</Overview>
  <ProductionCode></ProductionCode>
  <Rating></Rating>
  <RatingCount>0</RatingCount>
  <SeasonNumber>2</SeasonNumber>
  <Writer></Writer>
  <absolute_number></absolute_number>
  <filename></filename>
  <lastupdated>1418244391</lastupdated>
  <seasonid>507323</seasonid>
  <seriesid>264888</seriesid>
  <thumb_added></thumb_added>
  <thumb_height></thumb_height>
  <thumb_width></thumb_width>
</Episode>
<Episode>
  <id>4455007</id>
  <Combined_episodenumber>2</Combined_episodenumber>
  <Combined_season>2</Combined_season>
  <DVD_chapter></DVD_chapter>
  <DVD_discid></DVD_discid>
  <DVD_episodenumber></DVD_episodenumber>
  <DVD_season></DVD_season>
  <Director></Director>
  <EpImgFlag></EpImgFlag>
  <EpisodeName>Tofutastic</EpisodeName>
  <EpisodeNumber>2</EpisodeNumber>
  <FirstAired>2012-02-01</FirstAired>
  <GuestStars></GuestStars>
  <IMDB_ID></IMDB_ID>
  <Language>en</Language>
  <Overview>When Sadie discovers that her new crush, Taylor, is a committed vegetarian, she starts a campaign to get a veggie menu at the Y - but will Ashlii expose her as a fully-fledged meat eater? Meanwhile, Danny is stunned when he gets a good school report. Is this the end for him and Jake?

</Overview>
  <ProductionCode></ProductionCode>
  <Rating></Rating>
  <RatingCount>0</RatingCount>
  <SeasonNumber>2</SeasonNumber>
  <Writer></Writer>
  <absolute_number></absolute_number>
  <filename></filename>
  <lastupdated>1418244405</lastupdated>
  <seasonid>507323</seasonid>
  <seriesid>264888</seriesid>
  <thumb_added></thumb_added>
  <thumb_height></thumb_height>
  <thumb_width></thumb_width>
</Episode>
<Episode>
  <id>4455008</id>
  <Combined_episodenumber>3</Combined_episodenumber>
  <Combined_season>2</Combined_season>
  <DVD_chapter></DVD_chapter>
  <DVD_discid></DVD_discid>
  <DVD_episodenumber></DVD_episodenumber>
  <DVD_season></DVD_season>
  <Director></Director>
  <EpImgFlag></EpImgFlag>
  <EpisodeName>Gagalicious</EpisodeName>
  <EpisodeNumber>3</EpisodeNumber>
  <FirstAired>2012-02-08</FirstAired>
  <GuestStars></GuestStars>
  <IMDB_ID></IMDB_ID>
  <Language>en</Language>
  <Overview>When Kit's cousin comes to stay, Sadie and Dede think he's trying to turn Kit into someone different - but could it be Kit who feels he's got something to hide? Meanwhile, Danny and Jake try their hands at DJ-ing - but how far can they get with only Steve's old vinyl collection to work with?

</Overview>
  <ProductionCode></ProductionCode>
  <Rating></Rating>
  <RatingCount>0</RatingCount>
  <SeasonNumber>2</SeasonNumber>
  <Writer></Writer>
  <absolute_number></absolute_number>
  <filename></filename>
  <lastupdated>1355540099</lastupdated>
  <seasonid>507323</seasonid>
  <seriesid>264888</seriesid>
  <thumb_added></thumb_added>
  <thumb_height></thumb_height>
  <thumb_width></thumb_width>
</Episode>
<Episode>
  <id>4455009</id>
  <Combined_episodenumber>4</Combined_episodenumber>
  <Combined_season>2</Combined_season>
  <DVD_chapter></DVD_chapter>
  <DVD_discid></DVD_discid>
  <DVD_episodenumber></DVD_episodenumber>
  <DVD_season></DVD_season>
  <Director></Director>
  <EpImgFlag></EpImgFlag>
  <EpisodeName>Cocolocolistic</EpisodeName>
  <EpisodeNumber>4</EpisodeNumber>
  <FirstAired>2012-02-15</FirstAired>
  <GuestStars></GuestStars>
  <IMDB_ID></IMDB_ID>
  <Language>en</Language>
  <Overview>Sadie auditions to get into a new girl band, but when she upsets Kit once too often, he goes all out to get Whitney the gig in Sadie's place.

</Overview>
  <ProductionCode></ProductionCode>
  <Rating></Rating>
  <RatingCount>0</RatingCount>
  <SeasonNumber>2</SeasonNumber>
  <Writer></Writer>
  <absolute_number></absolute_number>
  <filename></filename>
  <lastupdated>1355540124</lastupdated>
  <seasonid>507323</seasonid>
  <seriesid>264888</seriesid>
  <thumb_added></thumb_added>
  <thumb_height></thumb_height>
  <thumb_width></thumb_width>
</Episode>
<Episode>
  <id>4455010</id>
  <Combined_episodenumber>5</Combined_episodenumber>
  <Combined_season>2</Combined_season>
  <DVD_chapter></DVD_chapter>
  <DVD_discid></DVD_discid>
  <DVD_episodenumber></DVD_episodenumber>
  <DVD_season></DVD_season>
  <Director></Director>
  <EpImgFlag></EpImgFlag>
  <EpisodeName>Blackmailamundo</EpisodeName>
  <EpisodeNumber>5</EpisodeNumber>
  <FirstAired>2012-02-22</FirstAired>
  <GuestStars></GuestStars>
  <IMDB_ID></IMDB_ID>
  <Language>en</Language>
  <Overview>Ashlii tries to blackmail Sadie, but Sadie has the last laugh when a certain boyband comes to call! Meanwhile, Keith kidnaps a dog for a good cause and Dede tries to teach the boys all about her favourite sci-fi show.

</Overview>
  <ProductionCode></ProductionCode>
  <Rating></Rating>
  <RatingCount>0</RatingCount>
  <SeasonNumber>2</SeasonNumber>
  <Writer></Writer>
  <absolute_number></absolute_number>
  <filename></filename>
  <lastupdated>1355540159</lastupdated>
  <seasonid>507323</seasonid>
  <seriesid>264888</seriesid>
  <thumb_added></thumb_added>
  <thumb_height></thumb_height>
  <thumb_width></thumb_width>
</Episode>
<Episode>
  <id>4455011</id>
  <Combined_episodenumber>6</Combined_episodenumber>
  <Combined_season>2</Combined_season>
  <DVD_chapter></DVD_chapter>
  <DVD_discid></DVD_discid>
  <DVD_episodenumber></DVD_episodenumber>
  <DVD_season></DVD_season>
  <Director></Director>
  <EpImgFlag></EpImgFlag>
  <EpisodeName>Bieberlicious</EpisodeName>
  <EpisodeNumber>6</EpisodeNumber>
  <FirstAired>2012-02-29</FirstAired>
  <GuestStars></GuestStars>
  <IMDB_ID></IMDB_ID>
  <Language>en</Language>
  <Overview>Sadie meddles with Ms V's love life just so she can be in a Justin Bieber video. But when her plans start to unravel, Sadie has to work extra hard to earn everyone's forgiveness.

</Overview>
  <ProductionCode></ProductionCode>
  <Rating></Rating>
  <RatingCount>0</RatingCount>
  <SeasonNumber>2</SeasonNumber>
  <Writer></Writer>
  <absolute_number></absolute_number>
  <filename></filename>
  <lastupdated>1355540208</lastupdated>
  <seasonid>507323</seasonid>
  <seriesid>264888</seriesid>
  <thumb_added></thumb_added>
  <thumb_height></thumb_height>
  <thumb_width></thumb_width>
</Episode>
<Episode>
  <id>4455012</id>
  <Combined_episodenumber>7</Combined_episodenumber>
  <Combined_season>2</Combined_season>
  <DVD_chapter></DVD_chapter>
  <DVD_discid></DVD_discid>
  <DVD_episodenumber></DVD_episodenumber>
  <DVD_season></DVD_season>
  <Director></Director>
  <EpImgFlag></EpImgFlag>
  <EpisodeName>Megatronic</EpisodeName>
  <EpisodeNumber>7</EpisodeNumber>
  <FirstAired>2012-03-07</FirstAired>
  <GuestStars></GuestStars>
  <IMDB_ID></IMDB_ID>
  <Language>en</Language>
  <Overview>Sadie uses bribery and corruption to beat Dede in the race to be deputy head girl, even though she really doesn't want the job.

</Overview>
  <ProductionCode></ProductionCode>
  <Rating></Rating>
  <RatingCount>0</RatingCount>
  <SeasonNumber>2</SeasonNumber>
  <Writer></Writer>
  <absolute_number></absolute_number>
  <filename></filename>
  <lastupdated>1355540274</lastupdated>
  <seasonid>507323</seasonid>
  <seriesid>264888</seriesid>
  <thumb_added></thumb_added>
  <thumb_height></thumb_height>
  <thumb_width></thumb_width>
</Episode>
<Episode>
  <id>4455013</id>
  <Combined_episodenumber>8</Combined_episodenumber>
  <Combined_season>2</Combined_season>
  <DVD_chapter></DVD_chapter>
  <DVD_discid></DVD_discid>
  <DVD_episodenumber></DVD_episodenumber>
  <DVD_season></DVD_season>
  <Director></Director>
  <EpImgFlag></EpImgFlag>
  <EpisodeName>Bridesmaidamundo</EpisodeName>
  <EpisodeNumber>8</EpisodeNumber>
  <FirstAired>2012-03-14</FirstAired>
  <GuestStars></GuestStars>
  <IMDB_ID></IMDB_ID>
  <Language>en</Language>
  <Overview>When Sadie interferes in her aunt's wedding, she discovers an uncomfortable truth from the past.

</Overview>
  <ProductionCode></ProductionCode>
  <Rating></Rating>
  <RatingCount>0</RatingCount>
  <SeasonNumber>2</SeasonNumber>
  <Writer></Writer>
  <absolute_number></absolute_number>
  <filename></filename>
  <lastupdated>1355540295</lastupdated>
  <seasonid>507323</seasonid>
  <seriesid>264888</seriesid>
  <thumb_added></thumb_added>
  <thumb_height></thumb_height>
  <thumb_width></thumb_width>
</Episode>
<Episode>
  <id>4455014</id>
  <Combined_episodenumber>9</Combined_episodenumber>
  <Combined_season>2</Combined_season>
  <DVD_chapter></DVD_chapter>
  <DVD_discid></DVD_discid>
  <DVD_episodenumber></DVD_episodenumber>
  <DVD_season></DVD_season>
  <Director></Director>
  <EpImgFlag></EpImgFlag>
  <EpisodeName>Moviemashupamundo</EpisodeName>
  <EpisodeNumber>9</EpisodeNumber>
  <FirstAired>2012-03-15</FirstAired>
  <GuestStars></GuestStars>
  <IMDB_ID></IMDB_ID>
  <Language>en</Language>
  <Overview>Sadie accidentally agrees to host a 'frightnight' movie night for Ashlii and Kalisha; unfortunately she's also supposed to be sharing a film night with Danny and Jake. Can she keep all the balls in the air? Or will the frightnight turn her home into a house of horror?

</Overview>
  <ProductionCode></ProductionCode>
  <Rating></Rating>
  <RatingCount>0</RatingCount>
  <SeasonNumber>2</SeasonNumber>
  <Writer></Writer>
  <absolute_number></absolute_number>
  <filename></filename>
  <lastupdated>1355540324</lastupdated>
  <seasonid>507323</seasonid>
  <seriesid>264888</seriesid>
  <thumb_added></thumb_added>
  <thumb_height></thumb_height>
  <thumb_width></thumb_width>
</Episode>
<Episode>
  <id>4455015</id>
  <Combined_episodenumber>10</Combined_episodenumber>
  <Combined_season>2</Combined_season>
  <DVD_chapter></DVD_chapter>
  <DVD_discid></DVD_discid>
  <DVD_episodenumber></DVD_episodenumber>
  <DVD_season></DVD_season>
  <Director></Director>
  <EpImgFlag></EpImgFlag>
  <EpisodeName>Jazperilliant</EpisodeName>
  <EpisodeNumber>10</EpisodeNumber>
  <FirstAired>2012-03-21</FirstAired>
  <GuestStars></GuestStars>
  <IMDB_ID></IMDB_ID>
  <Language>en</Language>
  <Overview>Danny loses Roger, while Steve and Keith lose their sense of proportion when they get sucked into the latest video game. Back at the Y club Dede offends Ms V's nephew when she uses him as a way to complete the '10 things to do before you're 14' list.

</Overview>
  <ProductionCode></ProductionCode>
  <Rating></Rating>
  <RatingCount>0</RatingCount>
  <SeasonNumber>2</SeasonNumber>
  <Writer></Writer>
  <absolute_number></absolute_number>
  <filename></filename>
  <lastupdated>1355540349</lastupdated>
  <seasonid>507323</seasonid>
  <seriesid>264888</seriesid>
  <thumb_added></thumb_added>
  <thumb_height></thumb_height>
  <thumb_width></thumb_width>
</Episode>
<Episode>
  <id>4455016</id>
  <Combined_episodenumber>11</Combined_episodenumber>
  <Combined_season>2</Combined_season>
  <DVD_chapter></DVD_chapter>
  <DVD_discid></DVD_discid>
  <DVD_episodenumber></DVD_episodenumber>
  <DVD_season></DVD_season>
  <Director></Director>
  <EpImgFlag></EpImgFlag>
  <EpisodeName>Bardalicious</EpisodeName>
  <EpisodeNumber>11</EpisodeNumber>
  <FirstAired>2012-03-22</FirstAired>
  <GuestStars></GuestStars>
  <IMDB_ID></IMDB_ID>
  <Language>en</Language>
  <Overview>When Kit stages a Shakespearian extravaganza, Sadie is desperate to play opposite Taylor - but will she be able to finally outsmart Ashlii? And when Imogen goes looking for a ballroom dancing partner, Danny and Jake discover that Steve's new apprentice is an expert; but how does Keith feel about the new arrival?

</Overview>
  <ProductionCode></ProductionCode>
  <Rating></Rating>
  <RatingCount>0</RatingCount>
  <SeasonNumber>2</SeasonNumber>
  <Writer></Writer>
  <absolute_number></absolute_number>
  <filename></filename>
  <lastupdated>1355540396</lastupdated>
  <seasonid>507323</seasonid>
  <seriesid>264888</seriesid>
  <thumb_added></thumb_added>
  <thumb_height></thumb_height>
  <thumb_width></thumb_width>
</Episode>
<Episode>
  <id>4455017</id>
  <Combined_episodenumber>12</Combined_episodenumber>
  <Combined_season>2</Combined_season>
  <DVD_chapter></DVD_chapter>
  <DVD_discid></DVD_discid>
  <DVD_episodenumber></DVD_episodenumber>
  <DVD_season></DVD_season>
  <Director></Director>
  <EpImgFlag></EpImgFlag>
  <EpisodeName>Pixiepoplistic (Part 1)</EpisodeName>
  <EpisodeNumber>12</EpisodeNumber>
  <FirstAired>2012-03-28</FirstAired>
  <GuestStars></GuestStars>
  <IMDB_ID></IMDB_ID>
  <Language>en</Language>
  <Overview>Dede has to pretend to be Sadie so that Pixie Lott will come and make a TV show in Sadie's living room. But can Dede overcome Ashlii's plotting and Keith's boisterous mates to win the event? And can she keep up the pretence that she isn't really Sadie?

</Overview>
  <ProductionCode></ProductionCode>
  <Rating></Rating>
  <RatingCount>0</RatingCount>
  <SeasonNumber>2</SeasonNumber>
  <Writer></Writer>
  <absolute_number></absolute_number>
  <filename></filename>
  <lastupdated>1355540430</lastupdated>
  <seasonid>507323</seasonid>
  <seriesid>264888</seriesid>
  <thumb_added></thumb_added>
  <thumb_height></thumb_height>
  <thumb_width></thumb_width>
</Episode>
<Episode>
  <id>4455047</id>
  <Combined_episodenumber>13</Combined_episodenumber>
  <Combined_season>2</Combined_season>
  <DVD_chapter></DVD_chapter>
  <DVD_discid></DVD_discid>
  <DVD_episodenumber></DVD_episodenumber>
  <DVD_season></DVD_season>
  <Director></Director>
  <EpImgFlag></EpImgFlag>
  <EpisodeName>Pixiepoplistic (Part 2)</EpisodeName>
  <EpisodeNumber>13</EpisodeNumber>
  <FirstAired>2012-03-29</FirstAired>
  <GuestStars></GuestStars>
  <IMDB_ID></IMDB_ID>
  <Language>en</Language>
  <Overview>When Dede is exposed as a fraud, she has to do all she can to convince the TV company that Pixie Lott should still come to Sadie's house. But will she and her friends get the chance to party with Pixie?

</Overview>
  <ProductionCode></ProductionCode>
  <Rating></Rating>
  <RatingCount>0</RatingCount>
  <SeasonNumber>2</SeasonNumber>
  <Writer></Writer>
  <absolute_number></absolute_number>
  <filename></filename>
  <lastupdated>1364612283</lastupdated>
  <seasonid>507323</seasonid>
  <seriesid>264888</seriesid>
  <thumb_added></thumb_added>
  <thumb_height></thumb_height>
  <thumb_width></thumb_width>
</Episode>
<Episode>
  <id>4819861</id>
  <Combined_episodenumber>1</Combined_episodenumber>
  <Combined_season>3</Combined_season>
  <DVD_chapter></DVD_chapter>
  <DVD_discid></DVD_discid>
  <DVD_episodenumber></DVD_episodenumber>
  <DVD_season></DVD_season>
  <Director></Director>
  <EpImgFlag></EpImgFlag>
  <EpisodeName>Beaudelicious</EpisodeName>
  <EpisodeNumber>1</EpisodeNumber>
  <FirstAired></FirstAired>
  <GuestStars></GuestStars>
  <IMDB_ID></IMDB_ID>
  <Language>en</Language>
  <Overview></Overview>
  <ProductionCode></ProductionCode>
  <Rating></Rating>
  <RatingCount>0</RatingCount>
  <SeasonNumber>3</SeasonNumber>
  <Writer></Writer>
  <absolute_number></absolute_number>
  <filename></filename>
  <lastupdated>1394274716</lastupdated>
  <seasonid>578963</seasonid>
  <seriesid>264888</seriesid>
  <thumb_added></thumb_added>
  <thumb_height></thumb_height>
  <thumb_width></thumb_width>
</Episode>
<Episode>
  <id>4819863</id>
  <Combined_episodenumber>2</Combined_episodenumber>
  <Combined_season>3</Combined_season>
  <DVD_chapter></DVD_chapter>
  <DVD_discid></DVD_discid>
  <DVD_episodenumber></DVD_episodenumber>
  <DVD_season></DVD_season>
  <Director></Director>
  <EpImgFlag></EpImgFlag>
  <EpisodeName>Mamalicious</EpisodeName>
  <EpisodeNumber>2</EpisodeNumber>
  <FirstAired></FirstAired>
  <GuestStars></GuestStars>
  <IMDB_ID></IMDB_ID>
  <Language>en</Language>
  <Overview>Sadie is really excited - it's Mother's Day, and she always does something exciting with her Dad on Mother's Day. However, Steve has gone off with his old mate Gary - leaving Sadie to spend the day with Bev.</Overview>
  <ProductionCode></ProductionCode>
  <Rating></Rating>
  <RatingCount>0</RatingCount>
  <SeasonNumber>3</SeasonNumber>
  <Writer></Writer>
  <absolute_number></absolute_number>
  <filename></filename>
  <lastupdated>1394274855</lastupdated>
  <seasonid>578963</seasonid>
  <seriesid>264888</seriesid>
  <thumb_added></thumb_added>
  <thumb_height></thumb_height>
  <thumb_width></thumb_width>
</Episode>
<Episode>
  <id>4819865</id>
  <Combined_episodenumber>3</Combined_episodenumber>
  <Combined_season>3</Combined_season>
  <DVD_chapter></DVD_chapter>
  <DVD_discid></DVD_discid>
  <DVD_episodenumber></DVD_episodenumber>
  <DVD_season></DVD_season>
  <Director></Director>
  <EpImgFlag></EpImgFlag>
  <EpisodeName>Braziliant</EpisodeName>
  <EpisodeNumber>3</EpisodeNumber>
  <FirstAired></FirstAired>
  <GuestStars></GuestStars>
  <IMDB_ID></IMDB_ID>
  <Language>en</Language>
  <Overview>Sadie is desperate to get some tickets to see One Direction at the local arena - but when her card is declined, she can't believe anyone else could have less luck than her - until Kit turns up.</Overview>
  <ProductionCode></ProductionCode>
  <Rating></Rating>
  <RatingCount>0</RatingCount>
  <SeasonNumber>3</SeasonNumber>
  <Writer></Writer>
  <absolute_number></absolute_number>
  <filename></filename>
  <lastupdated>1394274880</lastupdated>
  <seasonid>578963</seasonid>
  <seriesid>264888</seriesid>
  <thumb_added></thumb_added>
  <thumb_height></thumb_height>
  <thumb_width></thumb_width>
</Episode>
<Episode>
  <id>4819868</id>
  <Combined_episodenumber>4</Combined_episodenumber>
  <Combined_season>3</Combined_season>
  <DVD_chapter></DVD_chapter>
  <DVD_discid></DVD_discid>
  <DVD_episodenumber></DVD_episodenumber>
  <DVD_season></DVD_season>
  <Director></Director>
  <EpImgFlag></EpImgFlag>
  <EpisodeName>Ricolatino</EpisodeName>
  <EpisodeNumber>4</EpisodeNumber>
  <FirstAired></FirstAired>
  <GuestStars></GuestStars>
  <IMDB_ID></IMDB_ID>
  <Language>en</Language>
  <Overview>Ms V announces that she is holding a Bollywood theme night sponsored by her new squeeze Ajay. However Dede and Theresa turn detective and prove that Ajay is only dating Ms V so he can get building space for his new car park.</Overview>
  <ProductionCode></ProductionCode>
  <Rating></Rating>
  <RatingCount>0</RatingCount>
  <SeasonNumber>3</SeasonNumber>
  <Writer></Writer>
  <absolute_number></absolute_number>
  <filename></filename>
  <lastupdated>1394274900</lastupdated>
  <seasonid>578963</seasonid>
  <seriesid>264888</seriesid>
  <thumb_added></thumb_added>
  <thumb_height></thumb_height>
  <thumb_width></thumb_width>
</Episode>
<Episode>
  <id>4819870</id>
  <Combined_episodenumber>5</Combined_episodenumber>
  <Combined_season>3</Combined_season>
  <DVD_chapter></DVD_chapter>
  <DVD_discid></DVD_discid>
  <DVD_episodenumber></DVD_episodenumber>
  <DVD_season></DVD_season>
  <Director></Director>
  <EpImgFlag></EpImgFlag>
  <EpisodeName>Little Mixamondo</EpisodeName>
  <EpisodeNumber>5</EpisodeNumber>
  <FirstAired></FirstAired>
  <GuestStars></GuestStars>
  <IMDB_ID></IMDB_ID>
  <Language>en</Language>
  <Overview>Rico and Dede both enter the same website's competition to prove who is Sadie's best BFF, the prize being a trip for two to meet their favourite girl band, Little Mix.</Overview>
  <ProductionCode></ProductionCode>
  <Rating></Rating>
  <RatingCount>0</RatingCount>
  <SeasonNumber>3</SeasonNumber>
  <Writer></Writer>
  <absolute_number></absolute_number>
  <filename></filename>
  <lastupdated>1394274914</lastupdated>
  <seasonid>578963</seasonid>
  <seriesid>264888</seriesid>
  <thumb_added></thumb_added>
  <thumb_height></thumb_height>
  <thumb_width></thumb_width>
</Episode>
<Episode>
  <id>4819871</id>
  <Combined_episodenumber>6</Combined_episodenumber>
  <Combined_season>3</Combined_season>
  <DVD_chapter></DVD_chapter>
  <DVD_discid></DVD_discid>
  <DVD_episodenumber></DVD_episodenumber>
  <DVD_season></DVD_season>
  <Director></Director>
  <EpImgFlag></EpImgFlag>
  <EpisodeName>Dederama</EpisodeName>
  <EpisodeNumber>6</EpisodeNumber>
  <FirstAired></FirstAired>
  <GuestStars></GuestStars>
  <IMDB_ID></IMDB_ID>
  <Language>en</Language>
  <Overview>Dede has fallen in love with local hunk, Callum. At the same time she wins the 'Young Geneticist of the Year' award - which will be presented by world-famous scientist, Dr Vanda Viazanni.</Overview>
  <ProductionCode></ProductionCode>
  <Rating></Rating>
  <RatingCount>0</RatingCount>
  <SeasonNumber>3</SeasonNumber>
  <Writer></Writer>
  <absolute_number></absolute_number>
  <filename></filename>
  <lastupdated>1394274925</lastupdated>
  <seasonid>578963</seasonid>
  <seriesid>264888</seriesid>
  <thumb_added></thumb_added>
  <thumb_height></thumb_height>
  <thumb_width></thumb_width>
</Episode>
<Episode>
  <id>4819873</id>
  <Combined_episodenumber>7</Combined_episodenumber>
  <Combined_season>3</Combined_season>
  <DVD_chapter></DVD_chapter>
  <DVD_discid></DVD_discid>
  <DVD_episodenumber></DVD_episodenumber>
  <DVD_season></DVD_season>
  <Director></Director>
  <EpImgFlag></EpImgFlag>
  <EpisodeName>Dinnerlicious</EpisodeName>
  <EpisodeNumber>7</EpisodeNumber>
  <FirstAired></FirstAired>
  <GuestStars></GuestStars>
  <IMDB_ID></IMDB_ID>
  <Language>en</Language>
  <Overview>When Sadie thinks Taylor is about to dump her, she decides to go 'retro' and cook dinner for him - but when Sadie's Aunt and Uncle drop by, on their way to the local UFO support group, the evening gets weird.</Overview>
  <ProductionCode></ProductionCode>
  <Rating></Rating>
  <RatingCount>0</RatingCount>
  <SeasonNumber>3</SeasonNumber>
  <Writer></Writer>
  <absolute_number></absolute_number>
  <filename></filename>
  <lastupdated>1394274937</lastupdated>
  <seasonid>578963</seasonid>
  <seriesid>264888</seriesid>
  <thumb_added></thumb_added>
  <thumb_height></thumb_height>
  <thumb_width></thumb_width>
</Episode>
<Episode>
  <id>4819876</id>
  <Combined_episodenumber>8</Combined_episodenumber>
  <Combined_season>3</Combined_season>
  <DVD_chapter></DVD_chapter>
  <DVD_discid></DVD_discid>
  <DVD_episodenumber></DVD_episodenumber>
  <DVD_season></DVD_season>
  <Director></Director>
  <EpImgFlag></EpImgFlag>
  <EpisodeName>Seasonalicious</EpisodeName>
  <EpisodeNumber>8</EpisodeNumber>
  <FirstAired></FirstAired>
  <GuestStars></GuestStars>
  <IMDB_ID></IMDB_ID>
  <Language>en</Language>
  <Overview>Sadie's family have booked to go to 'Middlesummerfest' - the local music festival; she even manages to get Rico on board, once he realises that Bebe Bueno (his favourite Latin star of all time) is singing.</Overview>
  <ProductionCode></ProductionCode>
  <Rating></Rating>
  <RatingCount>0</RatingCount>
  <SeasonNumber>3</SeasonNumber>
  <Writer></Writer>
  <absolute_number></absolute_number>
  <filename></filename>
  <lastupdated>1394274947</lastupdated>
  <seasonid>578963</seasonid>
  <seriesid>264888</seriesid>
  <thumb_added></thumb_added>
  <thumb_height></thumb_height>
  <thumb_width></thumb_width>
</Episode>
<Episode>
  <id>4819878</id>
  <Combined_episodenumber>9</Combined_episodenumber>
  <Combined_season>3</Combined_season>
  <DVD_chapter></DVD_chapter>
  <DVD_discid></DVD_discid>
  <DVD_episodenumber></DVD_episodenumber>
  <DVD_season></DVD_season>
  <Director></Director>
  <EpImgFlag></EpImgFlag>
  <EpisodeName>Bobsleigh Bonkerlicious</EpisodeName>
  <EpisodeNumber>9</EpisodeNumber>
  <FirstAired></FirstAired>
  <GuestStars></GuestStars>
  <IMDB_ID></IMDB_ID>
  <Language>en</Language>
  <Overview>Dede is entering a bobsleigh race to raise money for a whale-tracking satellite system; but Sadie, who was supposed to find the 3rd racer, has completely forgotten to recruit someone.</Overview>
  <ProductionCode></ProductionCode>
  <Rating></Rating>
  <RatingCount>0</RatingCount>
  <SeasonNumber>3</SeasonNumber>
  <Writer></Writer>
  <absolute_number></absolute_number>
  <filename></filename>
  <lastupdated>1394274960</lastupdated>
  <seasonid>578963</seasonid>
  <seriesid>264888</seriesid>
  <thumb_added></thumb_added>
  <thumb_height></thumb_height>
  <thumb_width></thumb_width>
</Episode>
<Episode>
  <id>4819879</id>
  <Combined_episodenumber>10</Combined_episodenumber>
  <Combined_season>3</Combined_season>
  <DVD_chapter></DVD_chapter>
  <DVD_discid></DVD_discid>
  <DVD_episodenumber></DVD_episodenumber>
  <DVD_season></DVD_season>
  <Director></Director>
  <EpImgFlag></EpImgFlag>
  <EpisodeName>Bye Bye Babylicious</EpisodeName>
  <EpisodeNumber>10</EpisodeNumber>
  <FirstAired></FirstAired>
  <GuestStars></GuestStars>
  <IMDB_ID></IMDB_ID>
  <Language>en</Language>
  <Overview>In the final episode, there are big changes afoot for Sadie and the gang; and when it looks like she's going to lose her home and her favourite hangout, Sadie goes into protest mode; but really lies behind all the changes?</Overview>
  <ProductionCode></ProductionCode>
  <Rating></Rating>
  <RatingCount>0</RatingCount>
  <SeasonNumber>3</SeasonNumber>
  <Writer></Writer>
  <absolute_number></absolute_number>
  <filename></filename>
  <lastupdated>1394274980</lastupdated>
  <seasonid>578963</seasonid>
  <seriesid>264888</seriesid>
  <thumb_added></thumb_added>
  <thumb_height></thumb_height>
  <thumb_width></thumb_width>
</Episode>
</Data>