{"ID":235,"ShowID":89,"DateCreated":"2014-06-19T11:56:15Z","Number":1,"ParentalRating":"G","Image":"http://thetvdb.com/banners/seasons/254401-1.jpg","TVDB":480506,"Episodes":[{"ID":2158,"SeasonID":235,"ShowID":89,"MediaID":2161,"DateCreated":"2014-06-19T11:56:17Z","DatePublished":"2014-05-31T22:00:00Z","Number":1,"Title":"Spring Story","Plot":"The mice of Brambly Hedge throw a surprise birthday party for Wilfred Toadflax.","Runtime":26,"FirstAired":"1997-03-31T00:00:00Z","ParentalRating":"G","ParentalRatingReason":"G","Image":"http://thetvdb.com/banners/episodes/254401/4223184.jpg","TVDB":4223184},{"ID":2174,"SeasonID":235,"ShowID":89,"MediaID":2182,"DateCreated":"2014-06-19T11:56:29Z","DatePublished":"2014-05-31T22:00:00Z","Number":2,"Title":"Summer Story","Plot":"There is to be a wedding for Poppy and Dusty, and the planning begins.","Runtime":26,"FirstAired":"1997-08-25T00:00:00Z","ParentalRating":"G","ParentalRatingReason":"G","Image":"http://thetvdb.com/banners/episodes/254401/4223187.jpg","TVDB":4223187},{"ID":2155,"SeasonID":235,"ShowID":89,"MediaID":2156,"DateCreated":"2014-06-19T11:56:15Z","DatePublished":"2014-05-31T22:00:00Z","Number":3,"Title":"Autumn Story","Plot":"Primrose the mouse loses the way home just as a storm heads that way.","Runtime":26,"FirstAired":"1997-10-26T00:00:00Z","ParentalRating":"G","ParentalRatingReason":"G","Image":"http://thetvdb.com/banners/episodes/254401/4223190.jpg","TVDB":4223190},{"ID":2165,"SeasonID":235,"ShowID":89,"MediaID":2171,"DateCreated":"2014-06-19T11:56:23Z","DatePublished":"2014-05-31T22:00:00Z","Number":4,"Title":"Winter Story","Plot":"Brambly Hedge is home to a community of mice awaiting the winter Snow Ball.","Runtime":27,"FirstAired":"1996-12-25T00:00:00Z","ParentalRating":"G","ParentalRatingReason":"G","Image":"http://thetvdb.com/banners/episodes/254401/4223192.jpg","TVDB":4223192}],"EpisodeCount":4}
