{"ID":260,"ShowID":99,"DateCreated":"2014-06-19T14:04:08Z","Number":1,"ParentalRating":"R","Image":"http://thetvdb.com/banners/seasons/250487-1.jpg","TVDB":471302,"Episodes":[{"ID":2458,"SeasonID":260,"ShowID":99,"MediaID":2477,"DateCreated":"2014-06-19T14:04:43Z","DatePublished":"2014-05-31T22:00:00Z","Number":1,"Title":"Pilot","Plot":"A therapist and his family move across the country to escape their troubled past but quickly discover that their new home comes with its own horrific baggage.","Runtime":58,"FirstAired":"2011-10-05T00:00:00Z","Year":2011,"ParentalRating":"R16","ParentalRatingReason":"R16 Violence,horror and sex scenes","Director":"Ryan Murphy","Writer":"Ryan Murphy, Brad Falchuk","Rating":7.599999904632568,"RatingCount":171,"Image":"http://thetvdb.com/banners/episodes/250487/4147673.jpg","TVDB":4147673},{"ID":4478,"SeasonID":260,"ShowID":99,"MediaID":4498,"DateCreated":"2014-07-08T17:22:12Z","DatePublished":"2014-06-01T00:00:00Z","Number":2,"Title":"Home Invasion","Plot":"Vivien and Violet get themselves caught in a dangerous situation. Meanwhile, Ben goes back to Boston to fix a mistake that he made. ","Runtime":43,"FirstAired":"2011-10-12T00:00:00Z","Year":2011,"ParentalRating":"R16","ParentalRatingReason":"R16 Violence,horror and sex scenes","Director":"Alfonso Gomez-Rejon","Writer":"Ryan Murphy, Brad Falchuk","Rating":7.599999904632568,"RatingCount":155,"Image":"http://thetvdb.com/banners/episodes/250487/4180231.jpg","TVDB":4180231},{"ID":2457,"SeasonID":260,"ShowID":99,"MediaID":2475,"DateCreated":"2014-06-19T14:04:25Z","DatePublished":"2014-05-31T22:00:00Z","Number":3,"Title":"Murder House","Plot":"Vivien learns the horrific truth about the house's first residents and Ben's visitor causes him to further unravel about what really happened in the haunted house. Constance and Moira have their history revealed.","Runtime":43,"FirstAired":"2011-10-19T00:00:00Z","Year":2011,"ParentalRating":"R16","ParentalRatingReason":"R16 Violence,horror and sex scenes","Director":"Bradley Buecker","Writer":"Jennifer Salt","Rating":7.699999809265137,"RatingCount":144,"Image":"http://thetvdb.com/banners/episodes/250487/4183585.jpg","TVDB":4183585},{"ID":2981,"SeasonID":260,"ShowID":99,"MediaID":2999,"DateCreated":"2014-06-27T06:16:58Z","DatePublished":"2014-05-31T22:00:00Z","Number":4,"Title":"Halloween (1)","Plot":"The line between the living and the dead blurs on Halloween. Two of the house's previous residents give the Harmons decorating advice.","Runtime":39,"FirstAired":"2011-10-26T00:00:00Z","Year":2011,"ParentalRating":"R16","ParentalRatingReason":"R16 Violence,horror and sex scenes","Director":"David Semel","Writer":"James Wong","Rating":7.699999809265137,"RatingCount":132,"Image":"http://thetvdb.com/banners/episodes/250487/4189066.jpg","TVDB":4189066},{"ID":2766,"SeasonID":260,"ShowID":99,"MediaID":2784,"DateCreated":"2014-06-24T06:33:34Z","DatePublished":"2014-05-31T22:00:00Z","Number":5,"Title":"Halloween (2)","Plot":"Tate comes face to face with his past, and Ben and Vivien are haunted by a new houseguest before Halloween night comes to an end.","Runtime":41,"FirstAired":"2011-11-02T00:00:00Z","Year":2011,"ParentalRating":"R16","ParentalRatingReason":"R16 Violence,horror and sex scenes","Director":"David Semel","Writer":"Tim Minear","Rating":7.5,"RatingCount":134,"Image":"http://thetvdb.com/banners/episodes/250487/4191655.jpg","TVDB":4191655},{"ID":2455,"SeasonID":260,"ShowID":99,"MediaID":2473,"DateCreated":"2014-06-19T14:04:08Z","DatePublished":"2014-05-31T22:00:00Z","Number":6,"Title":"Piggy, Piggy","Plot":"Constance enlists Violet's assistance with Tate. Ben helps a new patient confront his fears.","Runtime":44,"FirstAired":"2011-11-09T00:00:00Z","Year":2011,"ParentalRating":"R16","ParentalRatingReason":"R16 Violence,horror and sex scenes","Director":"Mike Uppendahl","Writer":"Jessica Sharzer","Rating":7.400000095367432,"RatingCount":120,"Image":"http://thetvdb.com/banners/episodes/250487/4194085.jpg","TVDB":4194085},{"ID":4032,"SeasonID":260,"ShowID":99,"MediaID":4052,"DateCreated":"2014-07-04T17:41:29Z","DatePublished":"2014-06-01T00:00:00Z","Number":7,"Title":"Open House","Plot":"Moira persuades a buyer to make an offer while Constance and Larry work against her efforts.","Runtime":41,"FirstAired":"2011-11-16T00:00:00Z","Year":2011,"ParentalRating":"R16","ParentalRatingReason":"R16 Violence,horror and sex scenes","Director":"Tim Hunter","Writer":"Brad Falchuk","Rating":7.5,"RatingCount":116,"Image":"http://thetvdb.com/banners/episodes/250487/4194086.jpg","TVDB":4194086},{"ID":2757,"SeasonID":260,"ShowID":99,"MediaID":2775,"DateCreated":"2014-06-24T00:40:34Z","DatePublished":"2014-05-31T22:00:00Z","Number":8,"Title":"Rubber Man","Plot":"The man in the rubber suit is revealed.","Runtime":44,"FirstAired":"2011-11-23T00:00:00Z","Year":2011,"ParentalRating":"R16","ParentalRatingReason":"R16 Violence,horror and sex scenes","Director":"Miguel Arteta","Writer":"Ryan Murphy","Rating":7.5,"RatingCount":107,"Image":"http://thetvdb.com/banners/episodes/250487/4195857.jpg","TVDB":4195857},{"ID":7285,"SeasonID":260,"ShowID":99,"MediaID":7248,"DateCreated":"2014-08-17T08:09:01Z","DatePublished":"2014-06-01T00:00:00Z","Number":9,"Title":"Spooky Little Girl","Plot":"One of history's most famous murder victims pays the house a visit. Constance discovers more of Tate's bad behavior.","Runtime":41,"FirstAired":"2011-11-30T00:00:00Z","Year":2011,"ParentalRating":"R16","ParentalRatingReason":"R16 Violence,horror and sex scenes","Director":"John Scott","Writer":"Jennifer Salt","Rating":7.699999809265137,"RatingCount":106,"Image":"http://thetvdb.com/banners/episodes/250487/4195858.jpg","TVDB":4195858},{"ID":5238,"SeasonID":260,"ShowID":99,"MediaID":5168,"DateCreated":"2014-07-18T02:47:41Z","DatePublished":"2014-06-01T00:00:00Z","Number":10,"Title":"Smoldering Children","Plot":"Violet learns about the rules of the house. The truth about Larry's condition is explained. Constance is interrogated by the police.","Runtime":42,"FirstAired":"2011-12-07T00:00:00Z","Year":2011,"ParentalRating":"R16","ParentalRatingReason":"R16 Violence,horror and sex scenes","Director":"Michael Lehmann","Writer":"James Wong","Rating":7.800000190734863,"RatingCount":106,"Image":"http://thetvdb.com/banners/episodes/250487/4207785.jpg","TVDB":4207785},{"ID":2469,"SeasonID":260,"ShowID":99,"MediaID":2487,"DateCreated":"2014-06-19T14:05:25Z","DatePublished":"2014-05-31T22:00:00Z","Number":11,"Title":"Birth","Plot":"Vivien gives birth. Tate and Violet attempt to rid the house of some of its ghosts for good.","Runtime":42,"FirstAired":"2011-12-14T00:00:00Z","Year":2011,"ParentalRating":"R","Director":"Alfonso Gomez-Rejon","Writer":"Tim Minear","Rating":7.699999809265137,"RatingCount":96,"Image":"http://thetvdb.com/banners/episodes/250487/4207786.jpg","TVDB":4207786},{"ID":2456,"SeasonID":260,"ShowID":99,"MediaID":2474,"DateCreated":"2014-06-19T14:04:16Z","DatePublished":"2014-05-31T22:00:00Z","Number":12,"Title":"Afterbirth","Plot":"In the aftermath of family tragedy, Ben tries to take his child out of the Murder House. Meanwhile, Violet and Vivien accustom themselves to their new living arrangements, Constance raises Tate's child as her own and a new family buys the house.","Runtime":52,"FirstAired":"2011-12-21T00:00:00Z","Year":2011,"ParentalRating":"R","Director":"Bradley Buecker","Writer":"Jessica Sharzer","Rating":7.699999809265137,"RatingCount":95,"Image":"http://thetvdb.com/banners/episodes/250487/4207787.jpg","TVDB":4207787}],"EpisodeCount":12}
