{"ID":10010,"SeasonID":132,"ShowID":49,"MediaID":9991,"DateCreated":"2014-11-23T21:48:06Z","DatePublished":"2014-06-01T00:00:00Z","Number":18,"Title":"iDate a Bad Boy (1)","Plot":"Carly and Spencer become upset when their new neighbor Griffin steals the motorcycle that Carly bought for Spencer in iPromote Tech-Foots. Spencer lets Griffin off the hook, but Carly becomes upset. However, when Spencer later goes out to get smoothies, he returns to find Carly and Griffin kissing on the couch. Spencer becomes furious and paranoid, forces Griffin to leave, and forbids Carly to see him, though he eventually allows them to resume dating. Meanwhile, Sam pays Freddie $50 to make a w","Runtime":23,"FirstAired":"2009-05-09T00:00:00Z","ParentalRating":"PG","Rating":10,"RatingCount":1,"Image":"http://thetvdb.com/banners/episodes/82493/641621.jpg","TVDB":641621}
