{"ID":1004,"SeasonID":114,"ShowID":46,"MediaID":1005,"DateCreated":"2014-06-19T11:45:24Z","DatePublished":"2014-03-15T00:00:00Z","Number":2,"Title":"The Priest and The Beast","Plot":"Howard and Vince are up late, struggling to find a new musical direction in order to get signed the next morning by Pie Face Records. To inspire them, Naboo tells them the story of Rudy van Disarzio and Spider Dijon; the Bongo Brothers, who form the band Rudi \u0026 Spider. Rudi and Spider wander the desert in search of inspiration; looking for the New Sound. After an argument, Spider leaves with the intention of drumming for Carlos Santana, becoming temporarily distracted by a town populated only by","Runtime":30,"FirstAired":"2005-08-02T00:00:00Z","ParentalRating":"M","ParentalRatingReason":"Violence,sexual references and offensive language","Rating":8,"RatingCount":2,"Image":"http://thetvdb.com/banners/episodes/74302/295323.jpg","TVDB":295323}
