{"ID":10300,"SeasonID":767,"ShowID":314,"MediaID":10288,"DateCreated":"2014-12-16T08:59:55Z","DatePublished":"2014-12-01T00:00:00Z","Number":12,"Title":"Health Care and Cinema","Plot":"Kevin invites Jackie to a midnight rendezvous in order to give her a new wedding ring; the comatose movie critic wakes up but his tastes have radically changed.","Runtime":29,"FirstAired":"2009-08-24T00:00:00Z","Year":2009,"ParentalRating":"R","Director":"Scott Ellis","Writer":"Liz Brixius \u0026 Linda Wallem","Rating":7.5,"RatingCount":20,"Image":"http://thetvdb.com/banners/episodes/95731/737081.jpg","TVDB":737081}
