{"ID":1034,"SeasonID":124,"ShowID":18,"MediaID":1034,"DateCreated":"2014-06-19T11:45:40Z","DatePublished":"2014-03-15T00:00:00Z","Number":8,"Title":"The Empty Planet (2)","Plot":"Clyde and Rani only just manage to escape from the robots.\n\nRegrouping with Gavin in a cafe, Clyde deduces that he and Rani were left behind after the robots abducted everyone else because of the two of them having been 'grounded' by the Judoon, although this fails to explain Gavin's continued presence. When Gavin runs off again, Rani and Clyde are confronted by the robots, who explain that they want the 'son and heir' (Although Clyde initially assumes that they want Earth's sun and air); Gavin'","Runtime":27,"FirstAired":"2010-11-02T00:00:00Z","Year":2010,"ParentalRating":"PG","ParentalRatingReason":"PG Violence","Director":"Ashley Way","Writer":"Gareth Roberts","GuestStars":"Jocelyn Jee Esien, Ace Bhatti, Joe Maso, Paul Kasey, Ruari Mears, Jon Glover","Rating":7,"RatingCount":3,"Image":"http://thetvdb.com/banners/episodes/79708/2447331.jpg","TVDB":2447331}
