{"ID":10502,"SeasonID":788,"ShowID":319,"MediaID":10490,"DateCreated":"2014-12-17T03:15:14Z","DatePublished":"2014-12-01T00:00:00Z","Number":8,"Title":"Veritas","Plot":"Marty and the Pod participate in Galweather-Stearn's annual recruiting event, where the best and brightest from Harvard Business School are wined and dined. Marty takes the sole black recruit in the predominantly white affair under his wing; Doug tries to prove to Clyde that he can coach any of the potential candidates onto \"the list;\" Jeannie grills a sexy, flirtatious recruit to see if she's all style and no substance, but a secret of Jeannie's is revealed that makes her stance somewhat hypocr","Runtime":29,"FirstAired":"2012-03-04T00:00:00Z","Year":2012,"ParentalRating":"R18","ParentalRatingReason":"Drug use, sex scenes and offensive language","Director":"Stephen Hopkins","Writer":"Wesley S. Nickerson III","Rating":7.900000095367432,"RatingCount":43,"Image":"http://thetvdb.com/banners/episodes/247909/4256942.jpg","TVDB":4256942}
