{"ID":10663,"SeasonID":799,"ShowID":321,"MediaID":10651,"DateCreated":"2014-12-17T18:57:41Z","DatePublished":"2014-12-01T00:00:00Z","Number":17,"Title":"Ravenous","Plot":"When Marine dog tags are found in a national forest by a group of teens, the NCIS team is called in to investigate. While searching for the campsite of the Marine, the team finds out that there was another person, possibly a woman, with him. The investigation takes them to an even more higher discovery -- there could be a serial killer killing women in the national forest.","Runtime":44,"FirstAired":"2006-03-07T00:00:00Z","ParentalRating":"R","Director":"Thomas J. Wright","Writer":"Richard C. Arthur","GuestStars":"Todd Allen, Brian Dietzen, Michelle Harrison, Chris Payne Gilbert, Scott Anthony Leet","Rating":7.599999904632568,"RatingCount":34,"Image":"http://thetvdb.com/banners/episodes/72108/303574.jpg","IMDB":"tt0772567","TVDB":303574}
