{"ID":10764,"SeasonID":805,"ShowID":323,"MediaID":10752,"DateCreated":"2014-12-18T01:12:21Z","DatePublished":"2014-12-01T00:00:00Z","Number":4,"Title":"Scholar","Plot":"Farik decides to send biochemical student Eddy Pangetsu on a flight to Vancouver. There he must drive a shipment of real anthrax across the Canadian border to Los Angeles.","Runtime":57,"FirstAired":"2005-12-07T00:00:00Z","ParentalRating":"R16","ParentalRatingReason":"Violence, offensive language, sex scenes and content that may disturb","Rating":8.199999809265137,"RatingCount":6,"Image":"http://thetvdb.com/banners/episodes/74843/301855.jpg","TVDB":301855}
