{"ID":11038,"SeasonID":817,"ShowID":325,"MediaID":11026,"DateCreated":"2014-12-18T23:51:42Z","DatePublished":"2014-12-01T00:00:00Z","Number":18,"Title":"Mascara","Plot":"Langston is shocked when his former student is found murdered and becomes the focus of a CSI investigation into the world of Mexican wrestling.","Runtime":43,"FirstAired":"2009-04-02T00:00:00Z","ParentalRating":"R","Director":"William Friedkin","Writer":"Dustin Lee Abraham","GuestStars":"Liz Vassey, Carlos Carrasco, Matt O'Leary, Aimée Deshayes, Rey Gallegos, Aaron Aguilera","Rating":7.300000190734863,"RatingCount":31,"Image":"http://thetvdb.com/banners/episodes/72546/430697.jpg","IMDB":"tt1280101","TVDB":430697}
