{"ID":11092,"SeasonID":811,"ShowID":325,"MediaID":11081,"DateCreated":"2014-12-20T19:12:26Z","DatePublished":"2014-12-01T00:00:00Z","Number":3,"Title":"Let the Seller Beware","Plot":"Grissom and Catherine investigate the murder of a wealthy couple who are discovered outside  their glamorous home, which was up for sale. Sara probes the death of a cheerleader who is found eviscerated on a soccer field, her organs having been ingested by her killer.","Runtime":44,"FirstAired":"2002-10-10T00:00:00Z","Year":2002,"ParentalRating":"R16","ParentalRatingReason":"Drug use,violence and sexual references","Director":"Richard J. Lewis","Writer":"Andrew Lipsitz, Anthony E. Zuiker","GuestStars":"Chris Payne Gilbert, Mary-Margaret Humes, Taylor Handley, Nicole Paggi, Laurie Fortier, Monique Demers, Edward Edwards, Peter Asle Holden, Chris Johnson, Michael McLafferty, Rachel Shumate, Kendra D. Smith, Mary","Rating":7.699999809265137,"RatingCount":24,"Image":"http://thetvdb.com/banners/episodes/72546/89697.jpg","IMDB":"tt0534714","TVDB":89697}
