{"ID":11521,"SeasonID":849,"ShowID":66,"MediaID":11508,"DateCreated":"2015-02-22T21:54:20Z","DatePublished":"2015-03-06T00:00:00Z","Number":3,"Title":"Warrior's Fate","Plot":"King Ecbert visits the developing Viking settlement as the first harvest is sown and rebuffs criticism from his leading nobles. In Mercia, the Wessex/Viking forces charge at the battle at the Hill of the Ash. In Kattegat, Harbard arrives in to the Great Hall and his mysterious aura fascinates Aslaug and Helga but Siggy remains suspicious. There are strange and tragic happenings in Kattegat, and Siggy suspects Harbard is the cause.","Runtime":47,"FirstAired":"2015-03-06T00:00:00Z","Year":2015,"ParentalRating":"R16","ParentalRatingReason":"Violence","Director":"Jeff Woolnough","Writer":"Michael Hirst","GuestStars":"Amy Bailey, Moe Dunford, Maude Hirst, Gaia Weiss, Jefferson Hall, Jennie Jacques, John Kavanagh","Rating":7.699999809265137,"RatingCount":21,"Image":"http://thetvdb.com/banners/episodes/260449/5100642.jpg","IMDB":"tt3685792","TVDB":5100642}
