{"ID":11560,"SeasonID":858,"ShowID":39,"MediaID":11547,"DateCreated":"2015-02-27T02:34:28Z","DatePublished":"2015-03-15T00:00:00Z","Number":1,"Title":"Networked Nation","Plot":"Peter Mannion, the Secretary of State for Social Affairs, is told to launch his coalition partner Fergus's new 'Networked Nation' policy at a school. Peter doesn't even know how to right-click a mouse and would rather be celebrating his wedding anniversary, but Stewart Pearson won't hear otherwise. So Fergus is left in charge of drawing up a list of staff redundancies, and Terri Coverley is pretty sure she can make Fergus's hit list if she works hard at under-performing, and finds help from an u","Runtime":30,"FirstAired":"2012-09-08T00:00:00Z","Year":2012,"ParentalRating":"R16","ParentalRatingReason":"Lightbox Provisional Classification. Official NZ Rating To Be Confirmed.","Director":"Natalie Bailey","Writer":"Armando Iannucci, Simon Blackwell","Rating":8.399999618530273,"RatingCount":5,"Image":"http://thetvdb.com/banners/episodes/79843/4386768.jpg","TVDB":4386768}
