{"ID":11590,"SeasonID":860,"ShowID":9,"MediaID":11577,"DateCreated":"2015-02-27T07:11:01Z","DatePublished":"2015-03-15T00:00:00Z","Number":4,"Title":"Setting Out Your Stall","Plot":"New information links the unexplained death of a market trader to a series of drug rapes in east London - but with that case still ongoing, Ucos are unable to question the chief suspect, so they have to look into their victim's past in their search for clues. Gerry soon finds a likely culprit in the shape of the market inspector who clamped his car, while Sandra has problems of a more personal nature when her hated mother arrives for a visit.","Runtime":52,"FirstAired":"2011-07-25T00:00:00Z","ParentalRating":"M","ParentalRatingReason":"Lightbox Provisional Classification. Official NZ Rating To Be Confirmed.","Director":"Kenny Glenaan","Writer":"Lisa Holdsworth","GuestStars":"Sheila Hancock","Rating":8.300000190734863,"RatingCount":3,"Image":"http://thetvdb.com/banners/episodes/78823/4134625.jpg","TVDB":4134625}
