{"ID":11714,"SeasonID":869,"ShowID":341,"MediaID":11701,"DateCreated":"2015-02-28T21:56:08Z","DatePublished":"2015-01-15T00:00:00Z","Number":8,"Title":"Take Away","Plot":"Sheep can't order pizzas, can they? Noone told Shaun and pals, as they strip the scarecrow and head off into town.\n","Runtime":7,"FirstAired":"2007-03-13T00:00:00Z","ParentalRating":"G","ParentalRatingReason":"G","Rating":7.800000190734863,"RatingCount":20,"Image":"http://thetvdb.com/banners/episodes/79890/324663.jpg","TVDB":324663}
