{"ID":1871,"SeasonID":144,"ShowID":58,"MediaID":1870,"DateCreated":"2014-06-19T11:53:39Z","DatePublished":"2014-05-31T22:00:00Z","Number":9,"Title":"Andare Pescare","Plot":"Jax gets closer to the truth but there are still obstacles in his way.","Runtime":52,"FirstAired":"2012-11-06T00:00:00Z","Year":2012,"ParentalRating":"R18","ParentalRatingReason":"R18 Graphic violence and sex scenes","Director":"Billy Gierhart","Writer":"Liz Sagal ,  Kurt Sutter","Rating":7.699999809265137,"RatingCount":87,"Image":"http://thetvdb.com/banners/episodes/82696/4417766.jpg","TVDB":4417766}
