{"ID":2144,"SeasonID":190,"ShowID":74,"MediaID":2147,"DateCreated":"2014-06-19T11:56:10Z","DatePublished":"2014-05-31T22:00:00Z","Number":13,"Title":"Pickles","Plot":"When SpongeBob's enemy, Bubble Bass, comes in and orders a Krabby Patty, SpongeBob forgets to put the pickles in. Then, his whole world turns upside-down, literally. He even forgets how to make a Krabby Patty. Can he ever show his face in the Krusty Krab again?","Runtime":23,"FirstAired":"1999-10-28T00:00:00Z","ParentalRating":"G","Director":"Alan Smart, Walt Dohrn, Sherm Cohen","Writer":"Steven Fonti, Chris Mitchell, Peter Burns","Rating":7.199999809265137,"RatingCount":12,"Image":"http://thetvdb.com/banners/episodes/75886/179445.jpg","TVDB":179445}
