{"ID":2246,"SeasonID":181,"ShowID":58,"MediaID":2255,"DateCreated":"2014-06-19T11:57:15Z","DatePublished":"2014-05-31T22:00:00Z","Number":14,"Title":"To Be. Act 2","Plot":"Jax must overcome great obstacles as he attempts to finalize the gun deal between the Irish and the cartel.","Runtime":42,"FirstAired":"2011-12-06T00:00:00Z","Year":2011,"ParentalRating":"R","Director":"Kurt Sutter","Writer":"Kurt Sutter, Chris Collins","Rating":8.100000381469727,"RatingCount":109,"Image":"http://thetvdb.com/banners/episodes/82696/4198624.jpg","TVDB":4198624}
