{"ID":2314,"SeasonID":207,"ShowID":77,"MediaID":2332,"DateCreated":"2014-06-19T11:57:59Z","DatePublished":"2014-05-31T22:00:00Z","Number":7,"Title":"Night School","Plot":"Scott and the others are trapped inside the high school as the Alpha draws near. \n\n","Runtime":41,"FirstAired":"2011-07-11T00:00:00Z","Year":2011,"ParentalRating":"M","ParentalRatingReason":"Violence, horror and sexual references","Director":"Tim Andrew","Writer":"Jeff Vlaming","Rating":7.199999809265137,"RatingCount":42,"Image":"http://thetvdb.com/banners/episodes/175001/4125580.jpg","TVDB":4125580}
