{"ID":2685,"SeasonID":292,"ShowID":109,"MediaID":2702,"DateCreated":"2014-06-23T03:35:45Z","DatePublished":"2014-05-31T22:00:00Z","Number":9,"Title":"Absent Parents","Plot":"Monica has an unexpected visitor, her mother Joan, who no one's seen for twenty years. Suddenly all Monica's childhood insecurities come flooding back. But Joan has a secret, she's got Alzheimer's disease and has a very important task for Monica but, she can't remember what it is.  When Stan confesses to Yvonne that he's got a soft spot for her he gets a little more than he bargained for, in the stock room, up against the shelves and behind the frozen goods.  Yvonne is a woman with physical need","Runtime":48,"FirstAired":"2008-02-26T00:00:00Z","ParentalRating":"R16","ParentalRatingReason":"Violence, offensive language and sex scenes","Director":"Jim Loach","Writer":"Emma Frost","GuestStars":"Anne Reid","Rating":7.5,"RatingCount":2,"Image":"http://thetvdb.com/banners/episodes/78846/352955.jpg","TVDB":352955}
