{"ID":2782,"SeasonID":283,"ShowID":104,"MediaID":2800,"DateCreated":"2014-06-25T06:17:26Z","DatePublished":"2014-05-31T22:00:00Z","Number":19,"Title":"Daybreak (1)","Plot":"With Galactica on the verge of falling apart, Admiral Adama readies the ship for what could be its final mission, as Baltar's Six warns that humanity's final chapter is near.","Runtime":44,"FirstAired":"2009-03-13T00:00:00Z","ParentalRating":"R","Director":"Michael Rymer","Writer":"Ronald D. Moore","Rating":8,"RatingCount":99,"Image":"http://thetvdb.com/banners/episodes/73545/390809.jpg","IMDB":"tt0993920","TVDB":390809}
