{"ID":2832,"SeasonID":304,"ShowID":109,"MediaID":2850,"DateCreated":"2014-06-25T07:34:44Z","DatePublished":"2014-05-31T22:00:00Z","Number":6,"Title":"Gangster Gallagher","Plot":"It's Carl's 21st birthday, and Frank, Libby and the Maguires are planning a suprise party for him. Carl gets a job working for Jamie. However, his first job does not go to plan when Kelly steals money which was supposed to go to a business client. The business client in question is a ruthless psychopath. Left alone with him, Carl faces the most darkest experience of his life, and his problems have only just begun when Jamie accuses him of trying to steal from the family. Meanwhile, one of Joe's ","Runtime":49,"FirstAired":"2011-01-18T00:00:00Z","ParentalRating":"R16","ParentalRatingReason":"Violence, offensive language, drug use \u0026 sexual material","Director":"Metin Huseyin","Writer":"Darren Fairhurst","Rating":7.800000190734863,"RatingCount":4,"Image":"http://thetvdb.com/banners/episodes/78846/3472281.jpg","TVDB":3472281}
