{"ID":2846,"SeasonID":304,"ShowID":109,"MediaID":2864,"DateCreated":"2014-06-25T07:43:33Z","DatePublished":"2014-05-31T22:00:00Z","Number":22,"Title":"PC Gallagher","Plot":"Billy and Mimi find the game is up after Micky finds them in a compromising position. Billy is scared as the Maguire brothers want his blood for daring to marry their mother. Kelly's not sure about keeping the baby and Jamie ends up finding out more than he bargained for after he confronts her at work. Kelly realises she has to be honest with him but will he still want her and the baby. Carl sees a crime being committed but walks past, unaware of the consequences. Billy's stag ends up being a ni","Runtime":49,"FirstAired":"2011-10-25T00:00:00Z","ParentalRating":"R","Writer":"Jimmy Dowdall","Rating":8,"RatingCount":1,"Image":"http://thetvdb.com/banners/episodes/78846/3809111.jpg","TVDB":3809111}
