{"ID":3060,"SeasonID":311,"ShowID":111,"MediaID":3078,"DateCreated":"2014-06-27T10:32:23Z","DatePublished":"2014-06-01T00:00:00Z","Number":6,"Title":"It Ain't Easy Being J.D. McCoy","Plot":"Coach is furious with Tim and the team for a freshman hazing. J.D. wins the respect of the town and team. A late night swim at the lake turns into more for Julie and Matt. Tyra is shocked when a woman shows up claiming Cash owes her child support.","Runtime":43,"FirstAired":"2008-11-05T00:00:00Z","Year":2008,"ParentalRating":"M","ParentalRatingReason":"M Violence and sexual references","Director":"Patrick Norris","Writer":"Bridget Carpenter","Rating":7.599999904632568,"RatingCount":16,"Image":"http://thetvdb.com/banners/episodes/79337/402157.jpg","TVDB":402157}
