{"ID":3084,"SeasonID":315,"ShowID":111,"MediaID":3102,"DateCreated":"2014-06-27T18:03:46Z","DatePublished":"2014-06-01T00:00:00Z","Number":4,"Title":"Backfire","Plot":"Tim and Jason go to Mexico as Street hopes to explore experimental surgery. Riggins, who is worried about Street, turns to Lyla Garrity, who's busy helping a newcomer acclimate to Dillon. Meanwhile, Coach Taylor decides on a big career move that will change his life. A development in a police search deeply affects the lives of Tyra and Landry.","Runtime":43,"FirstAired":"2007-10-26T00:00:00Z","Year":2007,"ParentalRating":"M","ParentalRatingReason":"M Violence and sexual references","Director":"Jonas Pate","Writer":"David Hudgins","Rating":7.800000190734863,"RatingCount":14,"Image":"http://thetvdb.com/banners/episodes/79337/339560.jpg","TVDB":339560}
