{"ID":3601,"SeasonID":265,"ShowID":101,"MediaID":3620,"DateCreated":"2014-07-01T09:47:39Z","DatePublished":"2014-06-01T00:00:00Z","Number":12,"Title":"Operation Righteous Cowboy Lightning","Plot":"Liz tries to exploit the situation when a reality show follows Tracy's wife. Jack pre-tapes disaster telethons.","Runtime":21,"FirstAired":"2011-01-27T00:00:00Z","Year":2011,"ParentalRating":"M","Director":"Beth McCarthy Miller","Writer":"Robert Carlock","GuestStars":"Robert De Niro, Dean Winters","Rating":7.599999904632568,"RatingCount":61,"Image":"http://thetvdb.com/banners/episodes/79488/3511021.jpg","IMDB":"tt1635809","TVDB":3511021}
