{"ID":3648,"SeasonID":365,"ShowID":63,"MediaID":3667,"DateCreated":"2014-07-01T16:03:15Z","DatePublished":"2014-03-15T00:00:00Z","Number":10,"Title":"Midnight","Plot":"Location: Planet Midnight\nDate: unknown\nEnemies: unknown - possessive creature\n\nWhile visiting the planet Midnight, a beautiful and luxury planet, full of lavishs and hightech cities, a terrifying problem arises that leaves The Doctor powerless.","Runtime":46,"FirstAired":"2008-06-14T00:00:00Z","ParentalRating":"PG","ParentalRatingReason":"PG ","Director":"Alice Troughton","Writer":"Russell T. Davies","GuestStars":"David Troughton","Rating":7.900000095367432,"RatingCount":51,"Image":"http://thetvdb.com/banners/episodes/78804/368695.jpg","TVDB":368695}
