{"ID":3673,"SeasonID":371,"ShowID":7,"MediaID":3692,"DateCreated":"2014-07-01T20:31:54Z","DatePublished":"2014-03-15T00:00:00Z","Number":3,"Title":"Burn Out (1)","Plot":"A young woman, Marina sets fire to an abandoned car in a street and takes photographs of it as it burns. Boyd walks by and tackles her to the ground, attempting to shield her from the possible explosion.  He later learns that Marina's father died in a car accident a few years earlier in that spot, and Marina refuses to accept that his death was an accident.\n\nAlthough not officially a cold case, Boyd is intrigued and reluctantly agrees to investigate. Frankie runs forensic tests on Marina's fathe","Runtime":54,"FirstAired":"2001-06-25T00:00:00Z","ParentalRating":"M","ParentalRatingReason":"M Violence and offensive language","Director":"Edward Bennett","Writer":"Peter Jukes","GuestStars":"Leonard Webster,  Simon Kunz,  Peter Gallagher,  Beverley Hills,  Ralph Brown,  Clive Russell,  Angela Griffin","Rating":7.5,"RatingCount":4,"Image":"http://thetvdb.com/banners/episodes/79053/311588.jpg","TVDB":311588}
