{"ID":4179,"SeasonID":414,"ShowID":129,"MediaID":4199,"DateCreated":"2014-07-06T10:59:11Z","DatePublished":"2014-02-21T00:00:00Z","Number":4,"Title":"Green Light","Plot":"Walt loses control as he reacts to Skyler's news, endangering his job and relationships with Saul and Jesse. Hank throws himself into his blue meth investigation. Jesse enacts a new plan.","Runtime":47,"FirstAired":"2010-04-11T00:00:00Z","Year":2010,"ParentalRating":"R16","ParentalRatingReason":"R16 Violence and drug use","Director":"Scott Winant","Writer":"Sam Catlin","GuestStars":"Carmen Serano","Rating":7.5,"RatingCount":301,"Image":"http://thetvdb.com/banners/episodes/81189/2012411.jpg","IMDB":"tt1615554","TVDB":2012411}
