{"ID":4350,"SeasonID":273,"ShowID":101,"MediaID":4370,"DateCreated":"2014-07-07T00:48:03Z","DatePublished":"2014-06-01T00:00:00Z","Number":22,"Title":"Kidney Now!","Plot":"The TGS staff rallies as Jack's father's (Alan Alda) health hangs in the balance. Liz enjoys newfound fame as a relationship expert. When Tracy's high school invites him to speak at graduation, Kenneth helps him overcome embarrassing memories.","Runtime":21,"FirstAired":"2009-05-14T00:00:00Z","Year":2009,"ParentalRating":"M","Director":"Don Scardino","Writer":"Jack Burditt, Robert Carlock","GuestStars":"Alan Alda","Rating":7.599999904632568,"RatingCount":50,"Image":"http://thetvdb.com/banners/episodes/79488/556381.jpg","IMDB":"tt1248344","TVDB":556381}
