{"ID":442,"SeasonID":64,"ShowID":13,"MediaID":442,"DateCreated":"2014-06-19T11:40:00Z","DatePublished":"2014-03-15T00:00:00Z","Number":11,"Title":"No Joke for James","Plot":"One morning, James is boasting to Thomas and Percy that he is the smartest and most useful engine on the line. Thomas disagrees and thinks that all of The Fat Controller's engines are useful, and Percy tells James that he's getting all puffed up.","Runtime":6,"FirstAired":"1991-10-26T00:00:00Z","ParentalRating":"G","Rating":5}
