{"ID":4736,"SeasonID":436,"ShowID":161,"MediaID":4756,"DateCreated":"2014-07-10T08:46:47Z","DatePublished":"2014-06-01T00:00:00Z","Number":6,"Title":"Mr. Salt and Mrs. Pepper Day (3)","Plot":"With Mr. Salt and Mrs. Peppers' new baby on the way, Blue and Steve have decided to create \"\"Mr. Salt and Mrs. Pepper Day\"\" to honor them for all of the things they do to help everyone. Throughout the day, we try to help them out, from helping them to clean the kitchen to learning about their favorite things. They're also presented with a number of gifts carefully crafted to show them the things the characters appreciate about them. All of this is a great help to them - not only to relax, but al","Runtime":25,"FirstAired":"2001-10-15T00:00:00Z","Year":2001,"ParentalRating":"G","ParentalRatingReason":"G","Director":"Bruce Caines","Writer":"Michael T. Smith","GuestStars":"Matthew Cherry, Elijah Cunningham, Lauren Lawson, Ashley Ann Vega","TVDB":199155}
