{"ID":474,"SeasonID":66,"ShowID":5,"MediaID":474,"DateCreated":"2014-06-19T11:40:18Z","DatePublished":"2014-03-15T00:00:00Z","Number":8,"Title":"Tea Set Travis","Plot":"Bob, Wendy and the machines are picking up everyone's rubbish for recycling. Farmer Pickles is having a clear-out and he asks Travis to look after a very old tea set. Spud asks Travis to play hide and seek with him and when Bob, Wendy and the machines arrive, they take everything - including the tea set! Will Farmer Pickles catch them before they recycle the tea set?","Runtime":10,"FirstAired":"1999-07-22T00:00:00Z","ParentalRating":"G","ParentalRatingReason":"G","Rating":7.5,"RatingCount":2,"Image":"http://thetvdb.com/banners/episodes/78685/291867.jpg","TVDB":291867}
