{"ID":4756,"SeasonID":407,"ShowID":145,"MediaID":4776,"DateCreated":"2014-07-10T08:55:36Z","DatePublished":"2014-06-01T00:00:00Z","Number":3,"Title":"Mettle","Plot":"Mike and Tim are through to the quarter finals of Robot Wars, but trouble is brewing as a rival team who didn't get through decide to sabotage their efforts. Meanwhile, Brian is invited to do an installation at an art gallery, and Marsha goes along to offer support and enjoy the free booze.","Runtime":25,"FirstAired":"2001-03-09T00:00:00Z","ParentalRating":"R13","ParentalRatingReason":"Drug use, offensive language and sexual themes","Director":"Edgar Wright","Writer":"Simon Pegg, Jessica Stevenson","Rating":7.699999809265137,"RatingCount":7,"Image":"http://thetvdb.com/banners/episodes/72658/93121.jpg","TVDB":93121}
