{"ID":5069,"SeasonID":377,"ShowID":116,"MediaID":4999,"DateCreated":"2014-07-16T17:55:16Z","DatePublished":"2014-06-01T00:00:00Z","Number":21,"Title":"Je Souhaite","Plot":"Mulder and Scully discover a genie in a rug who, after 500 years of granting wishes, has come to the conclusion that people are still as greedy and self-centered as they always have been, and she begins to corrupt the wishes she grants if they are not specific enough.","Runtime":45,"FirstAired":"2000-05-14T00:00:00Z","ParentalRating":"M","Director":"Vince Gilligan","Writer":"Vince Gilligan","GuestStars":"Brett Bell, Paula Sorge, Will Sasso, Kevin Weisman, Paul Hayes","Rating":7.900000095367432,"RatingCount":20,"Image":"http://thetvdb.com/banners/episodes/77398/240629.jpg","IMDB":"tt0751145","TVDB":240629}
