{"ID":5076,"SeasonID":453,"ShowID":166,"MediaID":5006,"DateCreated":"2014-07-16T18:12:42Z","DatePublished":"2014-06-01T00:00:00Z","Number":17,"Title":"Dwight's Speech","Plot":"Dwight must confront his fear of public speaking when he is named Dunder-Mifflin's Salesman of the Year.  To prepare for a big convention where he is set to give a speech, Dwight turns to Michael to guide him in his quest to conquer the fear.  Meanwhile, Pam gets wrapped up with wedding plans, but Jim has plans of a different sort: an escape route out of Dunder-Mifflin and Scranton, at least for long enough so that he doesn't have to witness Pam's wedding.  While all of this is happening, the st","Runtime":21,"FirstAired":"2006-03-02T00:00:00Z","ParentalRating":"M","Director":"Charles McDougall","Writer":"Paul Lieberstein","GuestStars":"Creed Bratton, Mindy Kaling, Paul Lieberstein, Benjamin S. Carroll, John Kelly","Rating":7.699999809265137,"RatingCount":40,"Image":"http://thetvdb.com/banners/episodes/73244/306108.jpg","IMDB":"tt0770626","TVDB":306108}
