{"ID":5252,"SeasonID":478,"ShowID":171,"MediaID":5182,"DateCreated":"2014-07-18T06:43:49Z","DatePublished":"2014-02-21T00:00:00Z","Number":2,"Title":"Blood and Water","Plot":"Tension within the group begins to mount as the Strike Team attempt to rectify a mistake Vic made when he decided to use some of the cash from the stolen money train during a botched gun-running sting.  Meanwhile, Dutch and Claudette seek the help of a college honor student named Esteban who was the only survivor in the murder of two latin gang members, one of them being his close friend.","Runtime":46,"FirstAired":"2004-03-16T00:00:00Z","Year":2004,"ParentalRating":"R16","ParentalRatingReason":"R16 Violence,sexual violence and offensive language","Director":"Clark Johnson","Writer":"Charles H. Eglee, Kim Clements","GuestStars":"David Rees Snell, Cathy Cahlin Ryan, Ron Canada, Brian J. White, Jeremy Ray Valdez, Michele Hicks, Sticky Fingaz, Guillermo Diaz","Rating":7.400000095367432,"RatingCount":28,"Image":"http://thetvdb.com/banners/episodes/78261/277888.jpg","IMDB":"tt0699487","TVDB":277888}
