{"ID":5303,"SeasonID":486,"ShowID":151,"MediaID":5233,"DateCreated":"2014-07-19T04:44:04Z","DatePublished":"2014-02-21T00:00:00Z","Number":9,"Title":"Watch Your Backdraft","Plot":"Maya's tryst feeds office gossip, thanks to blabby Nina; Finch's scheme for a reserved parking space runs afoul of prying Elliott.","Runtime":22,"FirstAired":"2003-01-14T00:00:00Z","Year":2003,"ParentalRating":"M","ParentalRatingReason":"Lightbox Provisional Classification. Official NZ Rating To Be Confirmed.","GuestStars":"Danny Nucci","Rating":7,"RatingCount":1,"Image":"http://thetvdb.com/banners/episodes/71936/68318.jpg","TVDB":68318}
