{"ID":5332,"SeasonID":487,"ShowID":179,"MediaID":5262,"DateCreated":"2014-07-19T05:08:48Z","DatePublished":"2014-02-21T00:00:00Z","Number":10,"Title":"Blinded by the Light","Plot":"Having turned his back on the Murch, Trey arrives in L.A. to run the Silicon Beach investor circuit with Victoria. Back in San Francisco, Mitchell accompanies Nash to Michael Lau's birthday bash, and Hobbes gets closer with Trevor's mom, Joanne.","Runtime":25,"FirstAired":"2014-01-10T00:00:00Z","Year":2014,"ParentalRating":"M","ParentalRatingReason":"Lightbox Provisional Classification. Official NZ Rating To Be Confirmed.","Rating":9,"RatingCount":2,"Image":"http://thetvdb.com/banners/episodes/269003/4755919.jpg","TVDB":4755919}
