{"ID":5466,"SeasonID":483,"ShowID":172,"MediaID":5396,"DateCreated":"2014-07-21T08:27:47Z","DatePublished":"2014-02-21T00:00:00Z","Number":3,"Title":"Torture","Plot":"Franco begins to fear he's becoming Alicia's boy toy, while Tommy finds a way to end the fling between Damien and his science teacher. The rest of the crew also face their own problems - Lou is becoming real unstable emotionally, the chief has financial problems, and Sean is afraid of Tommy finding out who he's been sleeping with.\n","Runtime":46,"FirstAired":"2006-06-13T00:00:00Z","ParentalRating":"R16","ParentalRatingReason":"R16 Violence,sex scenes and content that may disturb","Director":"Jace Alexander","Writer":"Evan  Reilly","GuestStars":"Susan Sarandon,  Paige Turco","Rating":7.400000095367432,"RatingCount":10,"Image":"http://thetvdb.com/banners/episodes/73741/308417.jpg","TVDB":308417}
