{"ID":563,"SeasonID":70,"ShowID":13,"MediaID":563,"DateCreated":"2014-06-19T11:41:08Z","DatePublished":"2014-03-15T00:00:00Z","Number":10,"Title":"Toby and the Flood","Plot":"During many days of rain, Toby is asked to investigate a dam during rainy weather, and discovers it is about to burst its banks. Toby hurries to get to higher ground, but the bridge he is on is swept away after the dam collapses.","Runtime":6,"FirstAired":"1998-09-28T00:00:00Z","Year":1998,"ParentalRating":"G","ParentalRatingReason":"G","Rating":5}
