{"ID":5699,"SeasonID":78,"ShowID":22,"MediaID":5629,"DateCreated":"2014-07-23T09:11:23Z","DatePublished":"2014-06-01T00:00:00Z","Number":5,"Title":"Lies, Lies, Lies","Plot":"Jenny confides in her old college professor about her affair with Marina. Bette receives some delightful news. Dana's fears of being outed continue as she juggles between her tennis career and Lara. Alice's mother comes to stay with her daughter.\n","Runtime":53,"FirstAired":"2004-02-15T00:00:00Z","ParentalRating":"R16","ParentalRatingReason":"R16 Offensive language and sex scenes","Director":"Daniel Minahan","Writer":"Rose Troche","GuestStars":"Woody Jeffreys,  Matthew Currie Holmes,  Erwin Rosales,  Ivan Vance,  John Innes,  Deanne Henry,  Adrian Hough,  Landy Cannon,  Colin Cunningham,  Brad Dryborough,  Phil Hayes,  Anne Archer,  Anthony Sherwood,  A","Rating":7.300000190734863,"RatingCount":11,"Image":"http://thetvdb.com/banners/episodes/72477/87181.jpg","TVDB":87181}
