{"ID":5734,"SeasonID":516,"ShowID":177,"MediaID":5664,"DateCreated":"2014-07-23T10:33:23Z","DatePublished":"2014-06-01T00:00:00Z","Number":1,"Title":"The Doorway (1)","Plot":"Don and Megan take a trip to Hawaii for the holidays, Sally's friend visits the Francis family, a comedian torpedoes Peggy's Super Bowl ad campaign, and Roger gets some bad news about his mother.","Runtime":47,"FirstAired":"2013-04-07T00:00:00Z","ParentalRating":"M","ParentalRatingReason":"M Sex scenes,offensive language and drug use","Director":"Scott Hornbacher","Writer":"Matthew Weiner","GuestStars":"Linda Cardellini","Rating":7.300000190734863,"RatingCount":36,"Image":"http://thetvdb.com/banners/episodes/80337/4468357.jpg","IMDB":"tt2470504","TVDB":4468357}
