{"ID":5837,"SeasonID":523,"ShowID":115,"MediaID":5768,"DateCreated":"2014-07-26T08:29:57Z","DatePublished":"2014-06-01T00:00:00Z","Number":1,"Title":"Day 9: 11:00 A.M. - 12:00 P.M.","Plot":"After four years off the grid, Jack is apprehended in London by the CIA ? on the very day that President James Heller arrives. As the President faces political pressure over a US drone program run from a UK-based base, only disgraced agent Kate Morgan suspects that Jack's capture was all too easy.","Runtime":44,"FirstAired":"2014-05-05T00:00:00Z","Year":2014,"ParentalRating":"M","ParentalRatingReason":"Contains violence","Director":"Jon Cassar","Writer":"Evan Katz, Manny Coto","Rating":7.400000095367432,"RatingCount":64,"Image":"http://thetvdb.com/banners/episodes/76290/4769340.jpg","IMDB":"tt2911226","TVDB":4769340}
