{"ID":6480,"SeasonID":450,"ShowID":112,"MediaID":6368,"DateCreated":"2014-07-31T22:08:19Z","DatePublished":"2014-06-01T00:00:00Z","Number":16,"Title":"Bewitched, Bothered and Bewildered","Plot":"Xander tries to use Valentines Day to further his relationship with Cordelia but she succumbs to peer pressure and breaks up with him. With the help of Amy (who is exploring her mother's witch powers), he puts a love spell on her which goes horribly wrong, turning him into every woman's desire; except Cordelia's.","Runtime":45,"FirstAired":"1998-02-10T00:00:00Z","Year":1998,"ParentalRating":"M","Director":"James A. Contner","Writer":"Marti Noxon","GuestStars":"Lorna Scott, Jennie Chester, Kristen Winnicki, Tamara Braun, Scott Hamm, Robia LaMorte, Seth Green, Kristine Sutherland, Elizabeth Anne Allen, Mercedes McNab, James Marsters, Juliet Landau","Rating":8.100000381469727,"RatingCount":17,"Image":"http://thetvdb.com/banners/episodes/70327/29.jpg","TVDB":29}
