{"ID":6514,"SeasonID":551,"ShowID":175,"MediaID":6402,"DateCreated":"2014-07-31T23:33:06Z","DatePublished":"2014-02-21T00:00:00Z","Number":8,"Title":"The Tape","Plot":"George is excited about a new potential baldness cure that was discovered in China. While listening to a tape of his previous nights show, Jerry hears the voice of a mysterious woman who talks dirty into his tape recorder and everyone becomes excited by the voice. Elaine shines in an entirely new light for George when he is let in on the her secret, she's the voice. He is later driven crazy when she plays around with him while goofing around in front of Kramer's new video recorder. George tries ","Runtime":22,"FirstAired":"1991-11-13T00:00:00Z","ParentalRating":"PG","ParentalRatingReason":"PG Sexual references","Director":"David Steinberg","Writer":"Larry David, Bob Shaw, Don McEnery","GuestStars":"Larry David, Norman Brenner, John Apicella, Ping Wu","Rating":8,"RatingCount":31,"Image":"http://thetvdb.com/banners/episodes/79169/304084.jpg","TVDB":304084}
