{"ID":652,"SeasonID":90,"ShowID":36,"MediaID":650,"DateCreated":"2014-06-19T11:41:59Z","DatePublished":"2014-03-15T00:00:00Z","Number":1,"Title":"Learning To Fly, Part 1","Plot":"Country girl Tara Webster travels to Sydney to audition for the prestigious National Academy of Dance. It's a tumultuous week as she realises her dream of becoming a dancer is going to be a lot more difficult than she ever anticipated.","Runtime":25,"FirstAired":"2010-05-31T00:00:00Z","ParentalRating":"PG","ParentalRatingReason":"PG","Director":"Jeffery Walker","Writer":"Samatha Strauss","Rating":10,"RatingCount":1,"Image":"http://thetvdb.com/banners/episodes/167461/2321441.jpg","IMDB":"tt1587970","TVDB":2321441}
