{"ID":6556,"SeasonID":538,"ShowID":175,"MediaID":6444,"DateCreated":"2014-08-01T01:02:18Z","DatePublished":"2014-02-21T00:00:00Z","Number":4,"Title":"The Wink","Plot":"Elaine gets a blind date with the guy from her wake-up service; however, he likes dogs. A bit of grapefruit pulp, from Jerry's healthy breakfast, gets into George's eye and causes problems for him when his winks keep getting misinterpreted. Jerry's healthy diet conflicts with his dating of Elaine's cousin. Kramer promises a sick boy that Yankee Paul O'Neill will hit two home runs for him, so he can get back a birthday card that he sold based on George's wink.","Runtime":23,"FirstAired":"1995-10-12T00:00:00Z","ParentalRating":"PG","ParentalRatingReason":"PG Sexual references","Director":"Andy Ackerman","Writer":"Tom Gammill, Max Pross","GuestStars":"Larry David, Richard Herd, Brian McNamara, Tom Wright, Stacey Travis, Ian Patrick Williams, Paul O'Neill, Clive Rosengren, Thomas Dekker","Rating":7.699999809265137,"RatingCount":21,"Image":"http://thetvdb.com/banners/episodes/79169/304173.jpg","TVDB":304173}
