{"ID":6608,"SeasonID":540,"ShowID":181,"MediaID":6496,"DateCreated":"2014-08-01T02:03:16Z","DatePublished":"2014-02-21T00:00:00Z","Number":7,"Title":"Puss 'N' Glutes","Plot":"PJ and Stephanie take on the challenge of finding solid, stable women with which to build a relationship for Mike and Brendan.","Runtime":21,"FirstAired":"2010-09-05T00:00:00Z","Year":2010,"ParentalRating":"PG","ParentalRatingReason":"Lightbox Provisional Classification. Official NZ Rating To Be Confirmed.","Rating":7.300000190734863,"RatingCount":4,"Image":"http://thetvdb.com/banners/episodes/79600/2735861.jpg","TVDB":2735861}
