{"ID":6698,"SeasonID":561,"ShowID":201,"MediaID":6587,"DateCreated":"2014-08-02T04:54:12Z","DatePublished":"2014-06-01T00:00:00Z","Number":2,"Title":"Nicole \u0026 Trina","Plot":"Nicole has an incredibly unique type of obsession that keeps her from being able to enjoy time with her mother and brother.  If their hands aren't the way she wants them to be, she has a panic attack. And when her mother says any word with a \"K\" sound, Nicole has to make a strange noise with her throat. Meanwhile, Trina has constant  violent thoughts that torment her, such as \"Could I  hurt my best friend?\" and \"What if I  harmed that man?\" These horrible thoughts pop into her head with such con","Runtime":44,"FirstAired":"2009-06-01T00:00:00Z","ParentalRating":"M","ParentalRatingReason":"Lightbox Provisional Classification. Official NZ Rating To Be Confirmed.","TVDB":728871}
