{"ID":6752,"SeasonID":553,"ShowID":159,"MediaID":6641,"DateCreated":"2014-08-03T23:04:00Z","DatePublished":"2014-06-01T00:00:00Z","Number":13,"Title":"Super Map!","Plot":"Map finds a magic cape that gives him superpowers. Now, using his new superpowers, Map must lead Dora and Boots to Dora's house so her father can show her a surprise.","Runtime":24,"FirstAired":"2002-10-14T00:00:00Z","ParentalRating":"G","Rating":7,"RatingCount":1,"Image":"http://thetvdb.com/banners/episodes/74697/4445204.jpg","TVDB":4445204}
