{"ID":6829,"SeasonID":571,"ShowID":135,"MediaID":6718,"DateCreated":"2014-08-06T05:49:15Z","DatePublished":"2014-06-01T00:00:00Z","Number":16,"Title":"Wilson's Heart (2)","Plot":"In the aftermath of the bus accident, House struggles with his head injuries and short-term memory loss, and must deal with a concerned Wilson who believes his friend's health may be in danger.","Runtime":44,"FirstAired":"2008-05-19T00:00:00Z","ParentalRating":"M","Director":"Katie Jacobs","Writer":"Peter Blake (IV), David Foster (II), Garrett Lerner","GuestStars":"Ivana Milicevic","Rating":8.399999618530273,"RatingCount":74,"Image":"http://thetvdb.com/banners/episodes/73255/363829.jpg","IMDB":"tt1216109","TVDB":363829}
