{"ID":6930,"SeasonID":579,"ShowID":208,"MediaID":6822,"DateCreated":"2014-08-07T23:28:06Z","DatePublished":"2014-06-01T00:00:00Z","Number":6,"Title":"You're Gonna Change (Or I'm Gonna Leave)","Plot":"Rayna wants to change her sound and seeks out the help of a highly successful music producer, Liam McGuinnis; Juliette goes on a sham date with a squeaky-clean NFL quarterback as a PR move for her tarnished image; meanwhile, Lamar's plan to delay Coleman with a police traffic stop on his way to an important photo op for both candidates works too well, and Scarlett's relationship with Avery gets rocky.","Runtime":43,"FirstAired":"2012-11-14T00:00:00Z","Year":2012,"ParentalRating":"PG","ParentalRatingReason":"PG Violence, coarse language and sexual references","Director":"David Petrarca","Writer":"Meredith Lavender, Marcie Ulin","GuestStars":"Judith Hoag, Michiel Huisman, Rya Kihlstedt, Afton Williamson, Nicholas Strong, Tilky Jones, Kimberly Williams-Paisley, Ed Amatrudo, David Alford","Rating":8.300000190734863,"RatingCount":11,"Image":"http://thetvdb.com/banners/episodes/259055/4433689.jpg","IMDB":"tt2415114","TVDB":4433689}
