{"ID":7682,"SeasonID":599,"ShowID":212,"MediaID":7647,"DateCreated":"2014-08-24T12:24:30Z","DatePublished":"2014-06-01T00:00:00Z","Number":11,"Title":"Ducks and Tigers","Plot":"A visit from Esteban's daughter comes with new problems for Nancy. In the meantime, Isabelle joins Doug and Dean's scheme of revenge against Celia. ","Runtime":28,"FirstAired":"2009-08-17T00:00:00Z","Year":2009,"ParentalRating":"R","Director":"Matt Shakman","Writer":"Stephen Falk","Rating":7.400000095367432,"RatingCount":50,"Image":"http://thetvdb.com/banners/episodes/74845/982711.jpg","IMDB":"tt1447166","TVDB":982711}
