{"ID":7836,"SeasonID":618,"ShowID":174,"MediaID":7802,"DateCreated":"2014-08-26T05:04:46Z","DatePublished":"2014-06-01T00:00:00Z","Number":9,"Title":"Save the Duckling!","Plot":"When no pets need to be saved Ming-Ming goes out in search of pets to rescue and soon learns that she is the one who needs to be rescued.","Runtime":24,"FirstAired":"2006-03-15T00:00:00Z","Year":2006,"ParentalRating":"G","ParentalRatingReason":"G","Image":"http://thetvdb.com/banners/episodes/79377/310910.jpg","TVDB":310910}
