{"ID":8102,"SeasonID":607,"ShowID":213,"MediaID":8070,"DateCreated":"2014-08-27T23:02:58Z","DatePublished":"2014-06-01T00:00:00Z","Number":12,"Title":"The Ties that Bind (1)","Plot":"Kris and Junior face more brick walls when they decide to move to Alaska together. Meanwhile, Kris rides Wildfire in their final race together.","Runtime":42,"FirstAired":"2008-05-19T00:00:00Z","ParentalRating":"PG","Director":"Bradford May","Writer":"Loren Segan, Christina Lynch","GuestStars":"Tyra Danielle","Rating":6,"RatingCount":1,"IMDB":"tt1075631","TVDB":369806}
