{"ID":8386,"SeasonID":623,"ShowID":220,"MediaID":8349,"DateCreated":"2014-09-02T03:27:30Z","DatePublished":"2014-09-01T00:00:00Z","Number":12,"Title":"Fathers and Sons","Plot":"In order to work for the Marshal's Office, Raylan's dad Arlo agrees to become a double agent and work for Bo Crowder. Meanwhile, Bo sets up a meth lab to get back in business. ","Runtime":42,"FirstAired":"2010-06-01T00:00:00Z","ParentalRating":"M","Director":"Michael Katleman","Writer":"Dave Andron","GuestStars":"Raymond J. Barry, Alexandra Barreto, Jordi Caballero, Mo Gaffney, M.C. Gainey, Linda Gehringer, Rick Gomez, William Ragsdale, David Meunier, Ray Porter, Omar Avila, Joshua Bitton, Pat Skipper, Walton Goggins","Rating":7.599999904632568,"RatingCount":80,"Image":"http://thetvdb.com/banners/episodes/134241/1810171.jpg","IMDB":"tt1582924","TVDB":1810171}
