{"ID":8574,"SeasonID":437,"ShowID":162,"MediaID":8537,"DateCreated":"2014-09-05T17:43:15Z","DatePublished":"2014-06-01T00:00:00Z","Number":1,"Title":"Jefferson: My Name On A Plaque","Plot":"Rookie A.J. Cafaro questions if he is cut out for law enforcement after witnessing his first dead body; English teacher Hugh Herndon gives up teaching to go into law enforcement.","Runtime":21,"FirstAired":"2008-10-21T00:00:00Z","ParentalRating":"M","ParentalRatingReason":"M Content may disturb","TVDB":627311}
