{"ID":882,"SeasonID":109,"ShowID":43,"MediaID":883,"DateCreated":"2014-06-19T11:44:15Z","DatePublished":"2014-03-15T00:00:00Z","Number":8,"Title":"Top and Tail","Plot":"Spottywot's chair runs out of fuel, leaving him hanging from the ship's rail and he discovers he is not the only one who can swing from his hands","Runtime":10,"FirstAired":"2010-03-05T00:00:00Z","Year":2010,"ParentalRating":"G","ParentalRatingReason":"G","Image":"http://thetvdb.com/banners/episodes/105471/1931051.jpg","TVDB":1931051}
