{"ID":926,"SeasonID":118,"ShowID":18,"MediaID":926,"DateCreated":"2014-06-19T11:44:40Z","DatePublished":"2014-03-15T00:00:00Z","Number":5,"Title":"Secrets of the Stars (1)","Plot":"A fraudulent astrologer named Martin Trueman is hit by an extraterrestrial body and begins to impress everyone with his uncanny predictions. However, what he predicts for Sarah Jane is far from pleasant...","Runtime":30,"FirstAired":"2008-10-20T00:00:00Z","Year":2008,"ParentalRating":"PG","ParentalRatingReason":"PG Violence","Director":"Michael Kerrigan","Writer":"Gareth Roberts","GuestStars":"Russ Abbot, Mina Anwar, Ace Bhatti, Carryl Thomas, Nicky Ladanowski, Ed Hughes","Rating":7,"RatingCount":3,"Image":"http://thetvdb.com/banners/episodes/79708/399864.jpg","TVDB":399864}
