{"ID":9320,"SeasonID":677,"ShowID":247,"MediaID":9295,"DateCreated":"2014-10-06T22:02:30Z","DatePublished":"2014-09-01T00:00:00Z","Number":18,"Title":"Jamie's POV","Plot":"Jamie starts passing out flyers on the street, convinced that one in a hundred women that gets the paper will call him. Surprisingly, someone actually calls Jamie and meets with him at the coffee place, where she asks him about parties. Trying to pass an image other than his own, Jamie convinces Sasha and Rob to let him throw a party at their place, and bugs Sooz until she talks her brother into lending Jamie his DJ table. The party gets going but soon overcrowds, and Jamie's woman brings her hu","Runtime":25,"FirstAired":"2001-02-14T00:00:00Z","Year":2001,"ParentalRating":"R","TVDB":421707}
