{"ID":9457,"SeasonID":689,"ShowID":249,"MediaID":9432,"DateCreated":"2014-10-20T10:10:14Z","DatePublished":"2014-10-23T00:00:00Z","Number":2,"Title":"The Artful Dadger","Plot":"Valea becomes immersed in the art world, winning praise for his talent and unleashing the tortured artist within! However, bitter rivalry quickly ensues when Dad impresses the glitterarti and steals the lime light.","Runtime":23,"FirstAired":"2007-01-01T00:00:00Z","Year":2007,"ParentalRating":"M","ParentalRatingReason":"M Offensive language and sexual references","GuestStars":"John Reynolds, John Pule, Jenny Gibbs, Witi Ihimaera, Madeleine Sami as Ms Whotere","Image":"http://thetvdb.com/banners/episodes/75084/355095.jpg","TVDB":355095}
