{"ID":9679,"SeasonID":699,"ShowID":259,"MediaID":9654,"DateCreated":"2014-10-23T20:09:40Z","DatePublished":"2014-11-01T00:00:00Z","Number":5,"Title":"The Brown Identity","Plot":"Acting on a sudden urge to give back to the community, Jaquie decides to look after a girl with special needs but realises that philanthropy ain?t always easy. Jaquie?s agony is further fuelled as she is continually mistaken for Jackie Clarke, but when it results in her losing her invite to the fashion event of the year, their mutual disdain for each other reaches boiling point.","Runtime":23,"FirstAired":"2008-08-22T00:00:00Z","Year":2008,"ParentalRating":"M","ParentalRatingReason":"M Violence,sexual references and offensive language","Image":"http://thetvdb.com/banners/episodes/83511/400128.jpg","IMDB":"tt1279257","TVDB":400128}
