{"ID":9757,"SeasonID":392,"ShowID":139,"MediaID":9732,"DateCreated":"2014-10-30T21:24:11Z","DatePublished":"2014-06-01T00:00:00Z","Number":3,"Title":"The Capital Threat","Plot":"An examination of Washington, DC and all it's monuments. Plus, a look at the fate of Los Angeles.","Runtime":45,"FirstAired":"2009-05-05T00:00:00Z","Year":2009,"ParentalRating":"PG","ParentalRatingReason":"PG Drug references","Director":"Jim Hense","Writer":"Jim Hense","Rating":7.5,"RatingCount":2,"Image":"http://thetvdb.com/banners/episodes/83897/597251.jpg","IMDB":"tt1436933","TVDB":597251}
